[{"Date":"02\/01\/2024","GiaDieuChinh":4.16,"GiaDongCua":4.16,"KhoiLuongKhopLenh":6849900,"GiaTriKhopLenh":28704000000,"KLThoaThuan":0,"GtThoaThuan":0,"GiaMoCua":4.25,"GiaCaoNhat":4.25,"GiaThapNhat":4.15,"SoLenhMua":2125.0,"KLDatMua":15122900.0,"KLTB1LenhMua":7116.66,"SoLenhDatBan":2995.0,"KLDatBan":17991300.0,"KLTB1LenhBan":6007.0,"ChenhLechKL":"-2,868,400","ThayDoi":"0.02(0.48 %)"},{"Date":"03\/01\/2024","GiaDieuChinh":4.45,"GiaDongCua":4.45,"KhoiLuongKhopLenh":21527700,"GiaTriKhopLenh":93871000000,"KLThoaThuan":0,"GtThoaThuan":0,"GiaMoCua":4.14,"GiaCaoNhat":4.45,"GiaThapNhat":4.13,"SoLenhMua":4398.0,"KLDatMua":36668400.0,"KLTB1LenhMua":8337.52,"SoLenhDatBan":4486.0,"KLDatBan":30643300.0,"KLTB1LenhBan":6831.0,"ChenhLechKL":"6,025,100","ThayDoi":"0.29(6.97 %)"},{"Date":"04\/01\/2024","GiaDieuChinh":4.36,"GiaDongCua":4.36,"KhoiLuongKhopLenh":12936000,"GiaTriKhopLenh":57334000000,"KLThoaThuan":0,"GtThoaThuan":0,"GiaMoCua":4.54,"GiaCaoNhat":4.55,"GiaThapNhat":4.36,"SoLenhMua":3687.0,"KLDatMua":19888700.0,"KLTB1LenhMua":5394.28,"SoLenhDatBan":4721.0,"KLDatBan":36894500.0,"KLTB1LenhBan":7815.0,"ChenhLechKL":"-17,005,800","ThayDoi":"-0.09(-2.02 %)"},{"Date":"05\/01\/2024","GiaDieuChinh":4.28,"GiaDongCua":4.28,"KhoiLuongKhopLenh":10973000,"GiaTriKhopLenh":46903000000,"KLThoaThuan":0,"GtThoaThuan":0,"GiaMoCua":4.31,"GiaCaoNhat":4.4,"GiaThapNhat":4.2,"SoLenhMua":4621.0,"KLDatMua":23141900.0,"KLTB1LenhMua":5007.99,"SoLenhDatBan":2846.0,"KLDatBan":23520200.0,"KLTB1LenhBan":8264.0,"ChenhLechKL":"-378,300","ThayDoi":"-0.08(-1.83 %)"},{"Date":"08\/01\/2024","GiaDieuChinh":4.32,"GiaDongCua":4.32,"KhoiLuongKhopLenh":7955500,"GiaTriKhopLenh":34378000000,"KLThoaThuan":0,"GtThoaThuan":0,"GiaMoCua":4.31,"GiaCaoNhat":4.38,"GiaThapNhat":4.28,"SoLenhMua":2581.0,"KLDatMua":18530200.0,"KLTB1LenhMua":7179.47,"SoLenhDatBan":2638.0,"KLDatBan":19198700.0,"KLTB1LenhBan":7278.0,"ChenhLechKL":"-668,500","ThayDoi":"0.04(0.93 %)"},{"Date":"09\/01\/2024","GiaDieuChinh":4.32,"GiaDongCua":4.32,"KhoiLuongKhopLenh":6743700,"GiaTriKhopLenh":29388000000,"KLThoaThuan":0,"GtThoaThuan":0,"GiaMoCua":4.36,"GiaCaoNhat":4.44,"GiaThapNhat":4.3,"SoLenhMua":2312.0,"KLDatMua":14665400.0,"KLTB1LenhMua":6343.17,"SoLenhDatBan":3357.0,"KLDatBan":19967200.0,"KLTB1LenhBan":5948.0,"ChenhLechKL":"-5,301,800","ThayDoi":"0(0.00 %)"},{"Date":"10\/01\/2024","GiaDieuChinh":4.18,"GiaDongCua":4.18,"KhoiLuongKhopLenh":9634000,"GiaTriKhopLenh":40933000000,"KLThoaThuan":0,"GtThoaThuan":0,"GiaMoCua":4.33,"GiaCaoNhat":4.35,"GiaThapNhat":4.17,"SoLenhMua":0.0,"KLDatMua":0.0,"KLTB1LenhMua":0.0,"SoLenhDatBan":0.0,"KLDatBan":0.0,"KLTB1LenhBan":0.0,"ChenhLechKL":"0","ThayDoi":"-0.14(-3.24 %)"},{"Date":"11\/01\/2024","GiaDieuChinh":4.22,"GiaDongCua":4.22,"KhoiLuongKhopLenh":5738200,"GiaTriKhopLenh":24162000000,"KLThoaThuan":0,"GtThoaThuan":0,"GiaMoCua":4.19,"GiaCaoNhat":4.3,"GiaThapNhat":4.17,"SoLenhMua":null,"KLDatMua":null,"KLTB1LenhMua":null,"SoLenhDatBan":null,"KLDatBan":null,"KLTB1LenhBan":null,"ChenhLechKL":null,"ThayDoi":"0.04(0.96 %)"},{"Date":"12\/01\/2024","GiaDieuChinh":4.16,"GiaDongCua":4.16,"KhoiLuongKhopLenh":12910900,"GiaTriKhopLenh":53399000000,"KLThoaThuan":0,"GtThoaThuan":0,"GiaMoCua":4.2,"GiaCaoNhat":4.2,"GiaThapNhat":4.05,"SoLenhMua":null,"KLDatMua":null,"KLTB1LenhMua":null,"SoLenhDatBan":null,"KLDatBan":null,"KLTB1LenhBan":null,"ChenhLechKL":null,"ThayDoi":"-0.06(-1.42 %)"},{"Date":"15\/01\/2024","GiaDieuChinh":4.12,"GiaDongCua":4.12,"KhoiLuongKhopLenh":3921700,"GiaTriKhopLenh":16296000000,"KLThoaThuan":0,"GtThoaThuan":0,"GiaMoCua":4.16,"GiaCaoNhat":4.2,"GiaThapNhat":4.12,"SoLenhMua":null,"KLDatMua":null,"KLTB1LenhMua":null,"SoLenhDatBan":null,"KLDatBan":null,"KLTB1LenhBan":null,"ChenhLechKL":null,"ThayDoi":"-0.04(-0.96 %)"}]