[{"Date":"22\/08\/2024","GiaDieuChinh":9.81,"GiaDongCua":10.05,"KhoiLuongKhopLenh":3900.0,"GiaTriKhopLenh":39000000.0,"KLThoaThuan":0.0,"GtThoaThuan":0.0,"GiaMoCua":10.35,"GiaCaoNhat":10.35,"GiaThapNhat":10.05,"SoLenhMua":32.0,"KLDatMua":10300.0,"KLTB1LenhMua":321.88,"SoLenhDatBan":32.0,"KLDatBan":15100.0,"KLTB1LenhBan":472.0,"ChenhLechKL":"-4,800","ThayDoi":"-0.3(-2.90 %)"},{"Date":"20\/08\/2024","GiaDieuChinh":9.91,"GiaDongCua":10.15,"KhoiLuongKhopLenh":13900.0,"GiaTriKhopLenh":141000000.0,"KLThoaThuan":0.0,"GtThoaThuan":0.0,"GiaMoCua":10.75,"GiaCaoNhat":10.75,"GiaThapNhat":10.1,"SoLenhMua":56.0,"KLDatMua":32500.0,"KLTB1LenhMua":580.36,"SoLenhDatBan":56.0,"KLDatBan":41800.0,"KLTB1LenhBan":746.0,"ChenhLechKL":"-9,300","ThayDoi":"-0.5(-4.69 %)"},{"Date":"23\/08\/2024","GiaDieuChinh":10.11,"GiaDongCua":10.35,"KhoiLuongKhopLenh":1800.0,"GiaTriKhopLenh":18000000.0,"KLThoaThuan":0.0,"GtThoaThuan":0.0,"GiaMoCua":10.3,"GiaCaoNhat":10.55,"GiaThapNhat":10.05,"SoLenhMua":31.0,"KLDatMua":9200.0,"KLTB1LenhMua":296.77,"SoLenhDatBan":30.0,"KLDatBan":8300.0,"KLTB1LenhBan":277.0,"ChenhLechKL":"900","ThayDoi":"0.3(2.99 %)"},{"Date":"26\/08\/2024","GiaDieuChinh":10.11,"GiaDongCua":10.35,"KhoiLuongKhopLenh":400.0,"GiaTriKhopLenh":4000000.0,"KLThoaThuan":0.0,"GtThoaThuan":0.0,"GiaMoCua":10.4,"GiaCaoNhat":10.45,"GiaThapNhat":10.35,"SoLenhMua":14.0,"KLDatMua":3600.0,"KLTB1LenhMua":257.14,"SoLenhDatBan":33.0,"KLDatBan":14100.0,"KLTB1LenhBan":427.0,"ChenhLechKL":"-10,500","ThayDoi":"0(0.00 %)"},{"Date":"21\/08\/2024","GiaDieuChinh":10.11,"GiaDongCua":10.35,"KhoiLuongKhopLenh":500.0,"GiaTriKhopLenh":5000000.0,"KLThoaThuan":0.0,"GtThoaThuan":0.0,"GiaMoCua":10.4,"GiaCaoNhat":10.4,"GiaThapNhat":10.35,"SoLenhMua":23.0,"KLDatMua":15900.0,"KLTB1LenhMua":691.3,"SoLenhDatBan":36.0,"KLDatBan":29100.0,"KLTB1LenhBan":808.0,"ChenhLechKL":"-13,200","ThayDoi":"0.2(1.97 %)"},{"Date":"27\/08\/2024","GiaDieuChinh":10.16,"GiaDongCua":10.4,"KhoiLuongKhopLenh":500.0,"GiaTriKhopLenh":5000000.0,"KLThoaThuan":0.0,"GtThoaThuan":0.0,"GiaMoCua":10.3,"GiaCaoNhat":10.4,"GiaThapNhat":10.3,"SoLenhMua":16.0,"KLDatMua":4700.0,"KLTB1LenhMua":293.75,"SoLenhDatBan":21.0,"KLDatBan":9500.0,"KLTB1LenhBan":452.0,"ChenhLechKL":"-4,800","ThayDoi":"0.05(0.48 %)"},{"Date":"28\/08\/2024","GiaDieuChinh":10.16,"GiaDongCua":10.4,"KhoiLuongKhopLenh":2000.0,"GiaTriKhopLenh":20000000.0,"KLThoaThuan":0.0,"GtThoaThuan":0.0,"GiaMoCua":10.35,"GiaCaoNhat":10.4,"GiaThapNhat":10.35,"SoLenhMua":21.0,"KLDatMua":8000.0,"KLTB1LenhMua":380.95,"SoLenhDatBan":22.0,"KLDatBan":11100.0,"KLTB1LenhBan":505.0,"ChenhLechKL":"-3,100","ThayDoi":"0(0.00 %)"},{"Date":"29\/08\/2024","GiaDieuChinh":10.16,"GiaDongCua":10.4,"KhoiLuongKhopLenh":0.0,"GiaTriKhopLenh":0.0,"KLThoaThuan":0.0,"GtThoaThuan":0.0,"GiaMoCua":10.4,"GiaCaoNhat":10.4,"GiaThapNhat":10.4,"SoLenhMua":15.0,"KLDatMua":6900.0,"KLTB1LenhMua":460.0,"SoLenhDatBan":11.0,"KLDatBan":7400.0,"KLTB1LenhBan":673.0,"ChenhLechKL":"-500","ThayDoi":"0(0.00 %)"},{"Date":"30\/08\/2024","GiaDieuChinh":10.16,"GiaDongCua":10.4,"KhoiLuongKhopLenh":10500.0,"GiaTriKhopLenh":109000000.0,"KLThoaThuan":0.0,"GtThoaThuan":0.0,"GiaMoCua":10.4,"GiaCaoNhat":11.0,"GiaThapNhat":10.4,"SoLenhMua":36.0,"KLDatMua":17400.0,"KLTB1LenhMua":483.33,"SoLenhDatBan":44.0,"KLDatBan":30000.0,"KLTB1LenhBan":682.0,"ChenhLechKL":"-12,600","ThayDoi":"0(0.00 %)"},{"Date":"10\/09\/2024","GiaDieuChinh":10.35,"GiaDongCua":10.6,"KhoiLuongKhopLenh":0.0,"GiaTriKhopLenh":0.0,"KLThoaThuan":0.0,"GtThoaThuan":0.0,"GiaMoCua":10.6,"GiaCaoNhat":10.6,"GiaThapNhat":10.6,"SoLenhMua":null,"KLDatMua":null,"KLTB1LenhMua":null,"SoLenhDatBan":null,"KLDatBan":null,"KLTB1LenhBan":null,"ChenhLechKL":null,"ThayDoi":"0(0.00 %)"},{"Date":"09\/09\/2024","GiaDieuChinh":10.35,"GiaDongCua":10.6,"KhoiLuongKhopLenh":500.0,"GiaTriKhopLenh":5000000.0,"KLThoaThuan":0.0,"GtThoaThuan":0.0,"GiaMoCua":10.6,"GiaCaoNhat":10.6,"GiaThapNhat":10.6,"SoLenhMua":15.0,"KLDatMua":4100.0,"KLTB1LenhMua":273.33,"SoLenhDatBan":18.0,"KLDatBan":18200.0,"KLTB1LenhBan":1011.0,"ChenhLechKL":"-14,100","ThayDoi":"-0.2(-1.85 %)"},{"Date":"19\/08\/2024","GiaDieuChinh":10.4,"GiaDongCua":10.65,"KhoiLuongKhopLenh":8800.0,"GiaTriKhopLenh":89000000.0,"KLThoaThuan":0.0,"GtThoaThuan":0.0,"GiaMoCua":10.75,"GiaCaoNhat":10.75,"GiaThapNhat":10.15,"SoLenhMua":52.0,"KLDatMua":24100.0,"KLTB1LenhMua":463.46,"SoLenhDatBan":44.0,"KLDatBan":35700.0,"KLTB1LenhBan":811.0,"ChenhLechKL":"-11,600","ThayDoi":"-0.1(-0.93 %)"},{"Date":"16\/08\/2024","GiaDieuChinh":10.5,"GiaDongCua":10.75,"KhoiLuongKhopLenh":14700.0,"GiaTriKhopLenh":149000000.0,"KLThoaThuan":0.0,"GtThoaThuan":0.0,"GiaMoCua":10.4,"GiaCaoNhat":10.75,"GiaThapNhat":10.15,"SoLenhMua":58.0,"KLDatMua":21900.0,"KLTB1LenhMua":377.59,"SoLenhDatBan":49.0,"KLDatBan":39600.0,"KLTB1LenhBan":808.0,"ChenhLechKL":"-17,700","ThayDoi":"0(0.00 %)"},{"Date":"15\/08\/2024","GiaDieuChinh":10.5,"GiaDongCua":10.75,"KhoiLuongKhopLenh":3400.0,"GiaTriKhopLenh":35000000.0,"KLThoaThuan":0.0,"GtThoaThuan":0.0,"GiaMoCua":10.4,"GiaCaoNhat":10.75,"GiaThapNhat":10.4,"SoLenhMua":14.0,"KLDatMua":5300.0,"KLTB1LenhMua":378.57,"SoLenhDatBan":35.0,"KLDatBan":23500.0,"KLTB1LenhBan":671.0,"ChenhLechKL":"-18,200","ThayDoi":"-0.05(-0.46 %)"},{"Date":"04\/09\/2024","GiaDieuChinh":10.5,"GiaDongCua":10.75,"KhoiLuongKhopLenh":300.0,"GiaTriKhopLenh":3000000.0,"KLThoaThuan":0.0,"GtThoaThuan":0.0,"GiaMoCua":10.9,"GiaCaoNhat":10.9,"GiaThapNhat":10.75,"SoLenhMua":22.0,"KLDatMua":6200.0,"KLTB1LenhMua":281.82,"SoLenhDatBan":23.0,"KLDatBan":18800.0,"KLTB1LenhBan":817.0,"ChenhLechKL":"-12,600","ThayDoi":"0.35(3.37 %)"},{"Date":"05\/09\/2024","GiaDieuChinh":10.55,"GiaDongCua":10.8,"KhoiLuongKhopLenh":3600.0,"GiaTriKhopLenh":37000000.0,"KLThoaThuan":0.0,"GtThoaThuan":0.0,"GiaMoCua":10.15,"GiaCaoNhat":10.8,"GiaThapNhat":10.1,"SoLenhMua":27.0,"KLDatMua":6500.0,"KLTB1LenhMua":240.74,"SoLenhDatBan":35.0,"KLDatBan":35900.0,"KLTB1LenhBan":1026.0,"ChenhLechKL":"-29,400","ThayDoi":"0.05(0.47 %)"},{"Date":"06\/09\/2024","GiaDieuChinh":10.55,"GiaDongCua":10.8,"KhoiLuongKhopLenh":3600.0,"GiaTriKhopLenh":36000000.0,"KLThoaThuan":0.0,"GtThoaThuan":0.0,"GiaMoCua":10.2,"GiaCaoNhat":10.8,"GiaThapNhat":10.1,"SoLenhMua":24.0,"KLDatMua":23200.0,"KLTB1LenhMua":966.67,"SoLenhDatBan":28.0,"KLDatBan":27000.0,"KLTB1LenhBan":964.0,"ChenhLechKL":"-3,800","ThayDoi":"0(0.00 %)"},{"Date":"13\/08\/2024","GiaDieuChinh":10.55,"GiaDongCua":10.8,"KhoiLuongKhopLenh":300.0,"GiaTriKhopLenh":3000000.0,"KLThoaThuan":0.0,"GtThoaThuan":0.0,"GiaMoCua":10.4,"GiaCaoNhat":10.8,"GiaThapNhat":10.4,"SoLenhMua":9.0,"KLDatMua":1400.0,"KLTB1LenhMua":155.56,"SoLenhDatBan":18.0,"KLDatBan":11100.0,"KLTB1LenhBan":617.0,"ChenhLechKL":"-9,700","ThayDoi":"0(0.00 %)"},{"Date":"12\/08\/2024","GiaDieuChinh":10.55,"GiaDongCua":10.8,"KhoiLuongKhopLenh":400.0,"GiaTriKhopLenh":4000000.0,"KLThoaThuan":0.0,"GtThoaThuan":0.0,"GiaMoCua":10.4,"GiaCaoNhat":10.8,"GiaThapNhat":10.4,"SoLenhMua":14.0,"KLDatMua":3000.0,"KLTB1LenhMua":214.29,"SoLenhDatBan":17.0,"KLDatBan":12600.0,"KLTB1LenhBan":741.0,"ChenhLechKL":"-9,600","ThayDoi":"0(0.00 %)"},{"Date":"14\/08\/2024","GiaDieuChinh":10.55,"GiaDongCua":10.8,"KhoiLuongKhopLenh":4600.0,"GiaTriKhopLenh":48000000.0,"KLThoaThuan":0.0,"GtThoaThuan":0.0,"GiaMoCua":11.45,"GiaCaoNhat":11.5,"GiaThapNhat":10.4,"SoLenhMua":15.0,"KLDatMua":7200.0,"KLTB1LenhMua":480.0,"SoLenhDatBan":26.0,"KLDatBan":21100.0,"KLTB1LenhBan":812.0,"ChenhLechKL":"-13,900","ThayDoi":"0(0.00 %)"},{"Date":"08\/08\/2024","GiaDieuChinh":null,"GiaDongCua":null,"KhoiLuongKhopLenh":null,"GiaTriKhopLenh":null,"KLThoaThuan":null,"GtThoaThuan":null,"GiaMoCua":null,"GiaCaoNhat":null,"GiaThapNhat":null,"SoLenhMua":9.0,"KLDatMua":2100.0,"KLTB1LenhMua":233.33,"SoLenhDatBan":13.0,"KLDatBan":9500.0,"KLTB1LenhBan":731.0,"ChenhLechKL":"-7,400","ThayDoi":null}]