[{"Date":"15\/08\/2024","GiaDieuChinh":9.4,"GiaDongCua":9.4,"KhoiLuongKhopLenh":0,"GiaTriKhopLenh":0,"KLThoaThuan":0,"GtThoaThuan":0,"GiaMoCua":9.4,"GiaCaoNhat":9.4,"GiaThapNhat":9.4,"SoLenhMua":9,"KLDatMua":2600,"KLTB1LenhMua":288.89,"SoLenhDatBan":2,"KLDatBan":300,"KLTB1LenhBan":150,"ChenhLechKL":"2,300","ThayDoi":"0(0.00 %)"},{"Date":"14\/08\/2024","GiaDieuChinh":9.4,"GiaDongCua":9.4,"KhoiLuongKhopLenh":5,"GiaTriKhopLenh":47000,"KLThoaThuan":0,"GtThoaThuan":0,"GiaMoCua":9.4,"GiaCaoNhat":9.4,"GiaThapNhat":9.4,"SoLenhMua":8,"KLDatMua":4000,"KLTB1LenhMua":500.0,"SoLenhDatBan":3,"KLDatBan":400,"KLTB1LenhBan":133,"ChenhLechKL":"3,600","ThayDoi":"0(0.00 %)"},{"Date":"13\/08\/2024","GiaDieuChinh":9.4,"GiaDongCua":9.4,"KhoiLuongKhopLenh":200,"GiaTriKhopLenh":1880000,"KLThoaThuan":0,"GtThoaThuan":0,"GiaMoCua":9.4,"GiaCaoNhat":9.4,"GiaThapNhat":9.4,"SoLenhMua":4,"KLDatMua":1600,"KLTB1LenhMua":400.0,"SoLenhDatBan":8,"KLDatBan":2800,"KLTB1LenhBan":350,"ChenhLechKL":"-1,200","ThayDoi":"-0.7(-6.93 %)"},{"Date":"07\/08\/2024","GiaDieuChinh":9.4,"GiaDongCua":9.4,"KhoiLuongKhopLenh":1101,"GiaTriKhopLenh":10950400,"KLThoaThuan":0,"GtThoaThuan":0,"GiaMoCua":10.0,"GiaCaoNhat":10.0,"GiaThapNhat":9.4,"SoLenhMua":4,"KLDatMua":2200,"KLTB1LenhMua":550.0,"SoLenhDatBan":9,"KLDatBan":3600,"KLTB1LenhBan":400,"ChenhLechKL":"-1,400","ThayDoi":"-1(-9.62 %)"},{"Date":"01\/08\/2024","GiaDieuChinh":9.8,"GiaDongCua":9.8,"KhoiLuongKhopLenh":0,"GiaTriKhopLenh":0,"KLThoaThuan":0,"GtThoaThuan":0,"GiaMoCua":9.8,"GiaCaoNhat":9.8,"GiaThapNhat":9.8,"SoLenhMua":5,"KLDatMua":3400,"KLTB1LenhMua":680.0,"SoLenhDatBan":3,"KLDatBan":600,"KLTB1LenhBan":200,"ChenhLechKL":"2,800","ThayDoi":"0(0.00 %)"},{"Date":"02\/08\/2024","GiaDieuChinh":9.8,"GiaDongCua":9.8,"KhoiLuongKhopLenh":0,"GiaTriKhopLenh":0,"KLThoaThuan":0,"GtThoaThuan":0,"GiaMoCua":9.8,"GiaCaoNhat":9.8,"GiaThapNhat":9.8,"SoLenhMua":5,"KLDatMua":2400,"KLTB1LenhMua":480.0,"SoLenhDatBan":4,"KLDatBan":3000,"KLTB1LenhBan":750,"ChenhLechKL":"-600","ThayDoi":"0(0.00 %)"},{"Date":"05\/08\/2024","GiaDieuChinh":9.8,"GiaDongCua":9.8,"KhoiLuongKhopLenh":0,"GiaTriKhopLenh":0,"KLThoaThuan":0,"GtThoaThuan":0,"GiaMoCua":9.8,"GiaCaoNhat":9.8,"GiaThapNhat":9.8,"SoLenhMua":5,"KLDatMua":1900,"KLTB1LenhMua":380.0,"SoLenhDatBan":3,"KLDatBan":600,"KLTB1LenhBan":200,"ChenhLechKL":"1,300","ThayDoi":"0(0.00 %)"},{"Date":"09\/08\/2024","GiaDieuChinh":10.1,"GiaDongCua":10.1,"KhoiLuongKhopLenh":0,"GiaTriKhopLenh":0,"KLThoaThuan":0,"GtThoaThuan":0,"GiaMoCua":10.1,"GiaCaoNhat":10.1,"GiaThapNhat":10.1,"SoLenhMua":4,"KLDatMua":1800,"KLTB1LenhMua":450.0,"SoLenhDatBan":6,"KLDatBan":8800,"KLTB1LenhBan":1467,"ChenhLechKL":"-7,000","ThayDoi":"0(0.00 %)"},{"Date":"12\/08\/2024","GiaDieuChinh":10.1,"GiaDongCua":10.1,"KhoiLuongKhopLenh":0,"GiaTriKhopLenh":0,"KLThoaThuan":0,"GtThoaThuan":0,"GiaMoCua":10.1,"GiaCaoNhat":10.1,"GiaThapNhat":10.1,"SoLenhMua":3,"KLDatMua":1100,"KLTB1LenhMua":366.67,"SoLenhDatBan":4,"KLDatBan":1500,"KLTB1LenhBan":375,"ChenhLechKL":"-400","ThayDoi":"0(0.00 %)"},{"Date":"19\/08\/2024","GiaDieuChinh":10.1,"GiaDongCua":10.1,"KhoiLuongKhopLenh":0,"GiaTriKhopLenh":0,"KLThoaThuan":0,"GtThoaThuan":0,"GiaMoCua":10.1,"GiaCaoNhat":10.1,"GiaThapNhat":10.1,"SoLenhMua":3,"KLDatMua":500,"KLTB1LenhMua":166.67,"SoLenhDatBan":8,"KLDatBan":3100,"KLTB1LenhBan":388,"ChenhLechKL":"-2,600","ThayDoi":"0(0.00 %)"},{"Date":"20\/08\/2024","GiaDieuChinh":10.1,"GiaDongCua":10.1,"KhoiLuongKhopLenh":0,"GiaTriKhopLenh":0,"KLThoaThuan":0,"GtThoaThuan":0,"GiaMoCua":10.1,"GiaCaoNhat":10.1,"GiaThapNhat":10.1,"SoLenhMua":3,"KLDatMua":1500,"KLTB1LenhMua":500.0,"SoLenhDatBan":5,"KLDatBan":1000,"KLTB1LenhBan":200,"ChenhLechKL":"500","ThayDoi":"0(0.00 %)"},{"Date":"21\/08\/2024","GiaDieuChinh":10.1,"GiaDongCua":10.1,"KhoiLuongKhopLenh":0,"GiaTriKhopLenh":0,"KLThoaThuan":0,"GtThoaThuan":0,"GiaMoCua":10.1,"GiaCaoNhat":10.1,"GiaThapNhat":10.1,"SoLenhMua":3,"KLDatMua":1600,"KLTB1LenhMua":533.33,"SoLenhDatBan":6,"KLDatBan":2000,"KLTB1LenhBan":333,"ChenhLechKL":"-400","ThayDoi":"0(0.00 %)"},{"Date":"23\/08\/2024","GiaDieuChinh":10.1,"GiaDongCua":10.1,"KhoiLuongKhopLenh":0,"GiaTriKhopLenh":0,"KLThoaThuan":0,"GtThoaThuan":0,"GiaMoCua":10.1,"GiaCaoNhat":10.1,"GiaThapNhat":10.1,"SoLenhMua":4,"KLDatMua":2600,"KLTB1LenhMua":650.0,"SoLenhDatBan":8,"KLDatBan":3500,"KLTB1LenhBan":438,"ChenhLechKL":"-900","ThayDoi":"0(0.00 %)"},{"Date":"26\/08\/2024","GiaDieuChinh":10.1,"GiaDongCua":10.1,"KhoiLuongKhopLenh":0,"GiaTriKhopLenh":0,"KLThoaThuan":0,"GtThoaThuan":0,"GiaMoCua":10.1,"GiaCaoNhat":10.1,"GiaThapNhat":10.1,"SoLenhMua":6,"KLDatMua":3700,"KLTB1LenhMua":616.67,"SoLenhDatBan":6,"KLDatBan":2000,"KLTB1LenhBan":333,"ChenhLechKL":"1,700","ThayDoi":"0(0.00 %)"},{"Date":"27\/08\/2024","GiaDieuChinh":10.1,"GiaDongCua":10.1,"KhoiLuongKhopLenh":0,"GiaTriKhopLenh":0,"KLThoaThuan":0,"GtThoaThuan":0,"GiaMoCua":10.1,"GiaCaoNhat":10.1,"GiaThapNhat":10.1,"SoLenhMua":6,"KLDatMua":3700,"KLTB1LenhMua":616.67,"SoLenhDatBan":6,"KLDatBan":1200,"KLTB1LenhBan":200,"ChenhLechKL":"2,500","ThayDoi":"0(0.00 %)"},{"Date":"28\/08\/2024","GiaDieuChinh":10.1,"GiaDongCua":10.1,"KhoiLuongKhopLenh":0,"GiaTriKhopLenh":0,"KLThoaThuan":0,"GtThoaThuan":0,"GiaMoCua":10.1,"GiaCaoNhat":10.1,"GiaThapNhat":10.1,"SoLenhMua":3,"KLDatMua":2100,"KLTB1LenhMua":700.0,"SoLenhDatBan":6,"KLDatBan":1100,"KLTB1LenhBan":183,"ChenhLechKL":"1,000","ThayDoi":"0(0.00 %)"},{"Date":"22\/08\/2024","GiaDieuChinh":10.1,"GiaDongCua":10.1,"KhoiLuongKhopLenh":1,"GiaTriKhopLenh":10000,"KLThoaThuan":0,"GtThoaThuan":0,"GiaMoCua":10.1,"GiaCaoNhat":10.1,"GiaThapNhat":10.1,"SoLenhMua":3,"KLDatMua":1600,"KLTB1LenhMua":533.33,"SoLenhDatBan":9,"KLDatBan":2200,"KLTB1LenhBan":244,"ChenhLechKL":"-600","ThayDoi":"0(0.00 %)"},{"Date":"08\/08\/2024","GiaDieuChinh":10.1,"GiaDongCua":10.1,"KhoiLuongKhopLenh":100,"GiaTriKhopLenh":1010000,"KLThoaThuan":0,"GtThoaThuan":0,"GiaMoCua":10.1,"GiaCaoNhat":10.1,"GiaThapNhat":10.1,"SoLenhMua":15,"KLDatMua":6300,"KLTB1LenhMua":420.0,"SoLenhDatBan":4,"KLDatBan":8200,"KLTB1LenhBan":2050,"ChenhLechKL":"-1,900","ThayDoi":"0.7(7.45 %)"},{"Date":"16\/08\/2024","GiaDieuChinh":10.1,"GiaDongCua":10.1,"KhoiLuongKhopLenh":100,"GiaTriKhopLenh":1010000,"KLThoaThuan":0,"GtThoaThuan":0,"GiaMoCua":10.1,"GiaCaoNhat":10.1,"GiaThapNhat":10.1,"SoLenhMua":8,"KLDatMua":3300,"KLTB1LenhMua":412.5,"SoLenhDatBan":4,"KLDatBan":1100,"KLTB1LenhBan":275,"ChenhLechKL":"2,200","ThayDoi":"0.7(7.45 %)"},{"Date":"06\/08\/2024","GiaDieuChinh":10.4,"GiaDongCua":10.4,"KhoiLuongKhopLenh":1600,"GiaTriKhopLenh":15800000,"KLThoaThuan":0,"GtThoaThuan":0,"GiaMoCua":9.0,"GiaCaoNhat":10.4,"GiaThapNhat":9.0,"SoLenhMua":6,"KLDatMua":3900,"KLTB1LenhMua":650.0,"SoLenhDatBan":10,"KLDatBan":5300,"KLTB1LenhBan":530,"ChenhLechKL":"-1,400","ThayDoi":"0.6(6.12 %)"}]