[{"Date":"16\/01\/2024","GiaDieuChinh":3.03,"GiaDongCua":3.03,"KhoiLuongKhopLenh":34100.0,"GiaTriKhopLenh":103000000.0,"KLThoaThuan":0.0,"GtThoaThuan":0.0,"GiaMoCua":3.03,"GiaCaoNhat":3.03,"GiaThapNhat":3.01,"SoLenhMua":92.0,"KLDatMua":124400.0,"KLTB1LenhMua":1352.17,"SoLenhDatBan":43.0,"KLDatBan":122200.0,"KLTB1LenhBan":2842.0,"ChenhLechKL":"2,200","ThayDoi":"0(0.00 %)"},{"Date":"17\/01\/2024","GiaDieuChinh":3.01,"GiaDongCua":3.01,"KhoiLuongKhopLenh":62400.0,"GiaTriKhopLenh":188000000.0,"KLThoaThuan":0.0,"GtThoaThuan":0.0,"GiaMoCua":3.05,"GiaCaoNhat":3.05,"GiaThapNhat":3.0,"SoLenhMua":106.0,"KLDatMua":156500.0,"KLTB1LenhMua":1476.42,"SoLenhDatBan":65.0,"KLDatBan":209800.0,"KLTB1LenhBan":3228.0,"ChenhLechKL":"-53,300","ThayDoi":"-0.02(-0.66 %)"},{"Date":"18\/01\/2024","GiaDieuChinh":3.01,"GiaDongCua":3.01,"KhoiLuongKhopLenh":22900.0,"GiaTriKhopLenh":69000000.0,"KLThoaThuan":0.0,"GtThoaThuan":0.0,"GiaMoCua":3.01,"GiaCaoNhat":3.07,"GiaThapNhat":3.0,"SoLenhMua":94.0,"KLDatMua":102100.0,"KLTB1LenhMua":1086.17,"SoLenhDatBan":72.0,"KLDatBan":170500.0,"KLTB1LenhBan":2368.0,"ChenhLechKL":"-68,400","ThayDoi":"0(0.00 %)"},{"Date":"19\/01\/2024","GiaDieuChinh":3.02,"GiaDongCua":3.02,"KhoiLuongKhopLenh":28700.0,"GiaTriKhopLenh":86000000.0,"KLThoaThuan":0.0,"GtThoaThuan":0.0,"GiaMoCua":2.91,"GiaCaoNhat":3.07,"GiaThapNhat":2.91,"SoLenhMua":120.0,"KLDatMua":222700.0,"KLTB1LenhMua":1855.83,"SoLenhDatBan":67.0,"KLDatBan":140500.0,"KLTB1LenhBan":2097.0,"ChenhLechKL":"82,200","ThayDoi":"0.01(0.33 %)"},{"Date":"22\/01\/2024","GiaDieuChinh":3.01,"GiaDongCua":3.01,"KhoiLuongKhopLenh":19700.0,"GiaTriKhopLenh":59000000.0,"KLThoaThuan":0.0,"GtThoaThuan":0.0,"GiaMoCua":3.03,"GiaCaoNhat":3.05,"GiaThapNhat":3.01,"SoLenhMua":75.0,"KLDatMua":128500.0,"KLTB1LenhMua":1713.33,"SoLenhDatBan":60.0,"KLDatBan":121500.0,"KLTB1LenhBan":2025.0,"ChenhLechKL":"7,000","ThayDoi":"-0.01(-0.33 %)"},{"Date":"23\/01\/2024","GiaDieuChinh":3.0,"GiaDongCua":3.0,"KhoiLuongKhopLenh":206700.0,"GiaTriKhopLenh":622000000.0,"KLThoaThuan":0.0,"GtThoaThuan":0.0,"GiaMoCua":3.01,"GiaCaoNhat":3.01,"GiaThapNhat":3.0,"SoLenhMua":91.0,"KLDatMua":290800.0,"KLTB1LenhMua":3195.6,"SoLenhDatBan":65.0,"KLDatBan":290000.0,"KLTB1LenhBan":4462.0,"ChenhLechKL":"800","ThayDoi":"-0.01(-0.33 %)"},{"Date":"24\/01\/2024","GiaDieuChinh":3.0,"GiaDongCua":3.0,"KhoiLuongKhopLenh":63000.0,"GiaTriKhopLenh":189000000.0,"KLThoaThuan":0.0,"GtThoaThuan":0.0,"GiaMoCua":3.0,"GiaCaoNhat":3.04,"GiaThapNhat":3.0,"SoLenhMua":100.0,"KLDatMua":149400.0,"KLTB1LenhMua":1494.0,"SoLenhDatBan":69.0,"KLDatBan":216800.0,"KLTB1LenhBan":3142.0,"ChenhLechKL":"-67,400","ThayDoi":"0(0.00 %)"},{"Date":"25\/01\/2024","GiaDieuChinh":3.0,"GiaDongCua":3.0,"KhoiLuongKhopLenh":61500.0,"GiaTriKhopLenh":185000000.0,"KLThoaThuan":0.0,"GtThoaThuan":0.0,"GiaMoCua":3.01,"GiaCaoNhat":3.05,"GiaThapNhat":3.0,"SoLenhMua":103.0,"KLDatMua":137400.0,"KLTB1LenhMua":1333.98,"SoLenhDatBan":60.0,"KLDatBan":157200.0,"KLTB1LenhBan":2620.0,"ChenhLechKL":"-19,800","ThayDoi":"0(0.00 %)"},{"Date":"26\/01\/2024","GiaDieuChinh":2.99,"GiaDongCua":2.99,"KhoiLuongKhopLenh":61000.0,"GiaTriKhopLenh":183000000.0,"KLThoaThuan":0.0,"GtThoaThuan":0.0,"GiaMoCua":3.01,"GiaCaoNhat":3.01,"GiaThapNhat":2.99,"SoLenhMua":96.0,"KLDatMua":148200.0,"KLTB1LenhMua":1543.75,"SoLenhDatBan":59.0,"KLDatBan":181000.0,"KLTB1LenhBan":3068.0,"ChenhLechKL":"-32,800","ThayDoi":"-0.01(-0.33 %)"},{"Date":"29\/01\/2024","GiaDieuChinh":3.0,"GiaDongCua":3.0,"KhoiLuongKhopLenh":138700.0,"GiaTriKhopLenh":413000000.0,"KLThoaThuan":0.0,"GtThoaThuan":0.0,"GiaMoCua":2.99,"GiaCaoNhat":3.04,"GiaThapNhat":2.98,"SoLenhMua":87.0,"KLDatMua":239600.0,"KLTB1LenhMua":2754.02,"SoLenhDatBan":57.0,"KLDatBan":199000.0,"KLTB1LenhBan":3491.0,"ChenhLechKL":"40,600","ThayDoi":"0.01(0.33 %)"},{"Date":"30\/01\/2024","GiaDieuChinh":3.03,"GiaDongCua":3.03,"KhoiLuongKhopLenh":43500.0,"GiaTriKhopLenh":130000000.0,"KLThoaThuan":0.0,"GtThoaThuan":0.0,"GiaMoCua":3.0,"GiaCaoNhat":3.05,"GiaThapNhat":3.0,"SoLenhMua":71.0,"KLDatMua":123600.0,"KLTB1LenhMua":1740.85,"SoLenhDatBan":76.0,"KLDatBan":103400.0,"KLTB1LenhBan":1361.0,"ChenhLechKL":"20,200","ThayDoi":"0.03(1.00 %)"},{"Date":"31\/01\/2024","GiaDieuChinh":2.99,"GiaDongCua":2.99,"KhoiLuongKhopLenh":47900.0,"GiaTriKhopLenh":143000000.0,"KLThoaThuan":0.0,"GtThoaThuan":0.0,"GiaMoCua":3.0,"GiaCaoNhat":3.04,"GiaThapNhat":2.95,"SoLenhMua":147.0,"KLDatMua":225900.0,"KLTB1LenhMua":1536.73,"SoLenhDatBan":72.0,"KLDatBan":189600.0,"KLTB1LenhBan":2633.0,"ChenhLechKL":"36,300","ThayDoi":"-0.04(-1.32 %)"},{"Date":"01\/02\/2024","GiaDieuChinh":2.96,"GiaDongCua":2.96,"KhoiLuongKhopLenh":97800.0,"GiaTriKhopLenh":292000000.0,"KLThoaThuan":0.0,"GtThoaThuan":0.0,"GiaMoCua":2.98,"GiaCaoNhat":3.04,"GiaThapNhat":2.96,"SoLenhMua":100.0,"KLDatMua":194600.0,"KLTB1LenhMua":1946.0,"SoLenhDatBan":82.0,"KLDatBan":239900.0,"KLTB1LenhBan":2926.0,"ChenhLechKL":"-45,300","ThayDoi":"-0.03(-1.00 %)"},{"Date":"02\/02\/2024","GiaDieuChinh":2.96,"GiaDongCua":2.96,"KhoiLuongKhopLenh":77500.0,"GiaTriKhopLenh":230000000.0,"KLThoaThuan":0.0,"GtThoaThuan":0.0,"GiaMoCua":3.03,"GiaCaoNhat":3.03,"GiaThapNhat":2.94,"SoLenhMua":114.0,"KLDatMua":180100.0,"KLTB1LenhMua":1579.82,"SoLenhDatBan":94.0,"KLDatBan":190800.0,"KLTB1LenhBan":2030.0,"ChenhLechKL":"-10,700","ThayDoi":"0(0.00 %)"},{"Date":"05\/02\/2024","GiaDieuChinh":2.97,"GiaDongCua":2.97,"KhoiLuongKhopLenh":23000.0,"GiaTriKhopLenh":68000000.0,"KLThoaThuan":0.0,"GtThoaThuan":0.0,"GiaMoCua":3.04,"GiaCaoNhat":3.04,"GiaThapNhat":2.97,"SoLenhMua":67.0,"KLDatMua":85900.0,"KLTB1LenhMua":1282.09,"SoLenhDatBan":81.0,"KLDatBan":114300.0,"KLTB1LenhBan":1411.0,"ChenhLechKL":"-28,400","ThayDoi":"0.01(0.34 %)"},{"Date":"06\/02\/2024","GiaDieuChinh":3.0,"GiaDongCua":3.0,"KhoiLuongKhopLenh":25100.0,"GiaTriKhopLenh":75000000.0,"KLThoaThuan":0.0,"GtThoaThuan":0.0,"GiaMoCua":3.0,"GiaCaoNhat":3.02,"GiaThapNhat":2.98,"SoLenhMua":75.0,"KLDatMua":114800.0,"KLTB1LenhMua":1530.67,"SoLenhDatBan":56.0,"KLDatBan":101200.0,"KLTB1LenhBan":1807.0,"ChenhLechKL":"13,600","ThayDoi":"0.03(1.01 %)"},{"Date":"07\/02\/2024","GiaDieuChinh":2.95,"GiaDongCua":2.95,"KhoiLuongKhopLenh":50800.0,"GiaTriKhopLenh":151000000.0,"KLThoaThuan":0.0,"GtThoaThuan":0.0,"GiaMoCua":3.0,"GiaCaoNhat":3.01,"GiaThapNhat":2.95,"SoLenhMua":0.0,"KLDatMua":0.0,"KLTB1LenhMua":0.0,"SoLenhDatBan":0.0,"KLDatBan":0.0,"KLTB1LenhBan":0.0,"ChenhLechKL":"0","ThayDoi":"-0.05(-1.67 %)"},{"Date":"15\/02\/2024","GiaDieuChinh":3.02,"GiaDongCua":3.02,"KhoiLuongKhopLenh":25800.0,"GiaTriKhopLenh":77000000.0,"KLThoaThuan":0.0,"GtThoaThuan":0.0,"GiaMoCua":2.97,"GiaCaoNhat":3.06,"GiaThapNhat":2.97,"SoLenhMua":null,"KLDatMua":null,"KLTB1LenhMua":null,"SoLenhDatBan":null,"KLDatBan":null,"KLTB1LenhBan":null,"ChenhLechKL":null,"ThayDoi":"0.07(2.37 %)"},{"Date":"16\/02\/2024","GiaDieuChinh":2.97,"GiaDongCua":2.97,"KhoiLuongKhopLenh":74600.0,"GiaTriKhopLenh":223000000.0,"KLThoaThuan":0.0,"GtThoaThuan":0.0,"GiaMoCua":3.02,"GiaCaoNhat":3.03,"GiaThapNhat":2.97,"SoLenhMua":null,"KLDatMua":null,"KLTB1LenhMua":null,"SoLenhDatBan":null,"KLDatBan":null,"KLTB1LenhBan":null,"ChenhLechKL":null,"ThayDoi":"-0.05(-1.66 %)"},{"Date":"19\/02\/2024","GiaDieuChinh":2.99,"GiaDongCua":2.99,"KhoiLuongKhopLenh":221800.0,"GiaTriKhopLenh":662000000.0,"KLThoaThuan":0.0,"GtThoaThuan":0.0,"GiaMoCua":3.0,"GiaCaoNhat":3.0,"GiaThapNhat":2.97,"SoLenhMua":null,"KLDatMua":null,"KLTB1LenhMua":null,"SoLenhDatBan":null,"KLDatBan":null,"KLTB1LenhBan":null,"ChenhLechKL":null,"ThayDoi":"0.02(0.67 %)"},{"Date":"11\/01\/2024","GiaDieuChinh":null,"GiaDongCua":null,"KhoiLuongKhopLenh":null,"GiaTriKhopLenh":null,"KLThoaThuan":null,"GtThoaThuan":null,"GiaMoCua":null,"GiaCaoNhat":null,"GiaThapNhat":null,"SoLenhMua":102.0,"KLDatMua":173000.0,"KLTB1LenhMua":1696.08,"SoLenhDatBan":82.0,"KLDatBan":171000.0,"KLTB1LenhBan":2085.0,"ChenhLechKL":"2,000","ThayDoi":null},{"Date":"12\/01\/2024","GiaDieuChinh":null,"GiaDongCua":null,"KhoiLuongKhopLenh":null,"GiaTriKhopLenh":null,"KLThoaThuan":null,"GtThoaThuan":null,"GiaMoCua":null,"GiaCaoNhat":null,"GiaThapNhat":null,"SoLenhMua":114.0,"KLDatMua":115300.0,"KLTB1LenhMua":1011.4,"SoLenhDatBan":80.0,"KLDatBan":150800.0,"KLTB1LenhBan":1885.0,"ChenhLechKL":"-35,500","ThayDoi":null},{"Date":"15\/01\/2024","GiaDieuChinh":null,"GiaDongCua":null,"KhoiLuongKhopLenh":null,"GiaTriKhopLenh":null,"KLThoaThuan":null,"GtThoaThuan":null,"GiaMoCua":null,"GiaCaoNhat":null,"GiaThapNhat":null,"SoLenhMua":68.0,"KLDatMua":106300.0,"KLTB1LenhMua":1563.24,"SoLenhDatBan":53.0,"KLDatBan":124000.0,"KLTB1LenhBan":2340.0,"ChenhLechKL":"-17,700","ThayDoi":null}]