[{"Date":"01\/10\/2024","GiaDieuChinh":28.7,"GiaDongCua":28.7,"KhoiLuongKhopLenh":446763,"GiaTriKhopLenh":12768775500,"KLThoaThuan":303000,"GtThoaThuan":8620200000,"GiaMoCua":28.5,"GiaCaoNhat":28.9,"GiaThapNhat":28.3,"SoLenhMua":419,"KLDatMua":618200,"KLTB1LenhMua":1475.42,"SoLenhDatBan":502,"KLDatBan":516700,"KLTB1LenhBan":1029,"ChenhLechKL":"101,500","ThayDoi":"0.2(0.70 %)"},{"Date":"22\/10\/2024","GiaDieuChinh":28.4,"GiaDongCua":28.4,"KhoiLuongKhopLenh":472700,"GiaTriKhopLenh":13422150000,"KLThoaThuan":0,"GtThoaThuan":0,"GiaMoCua":28.5,"GiaCaoNhat":28.5,"GiaThapNhat":28.2,"SoLenhMua":523,"KLDatMua":642000,"KLTB1LenhMua":1227.53,"SoLenhDatBan":423,"KLDatBan":547100,"KLTB1LenhBan":1293,"ChenhLechKL":"94,900","ThayDoi":"-0.1(-0.35 %)"},{"Date":"02\/10\/2024","GiaDieuChinh":28.4,"GiaDongCua":28.4,"KhoiLuongKhopLenh":505956,"GiaTriKhopLenh":14396809200,"KLThoaThuan":0,"GtThoaThuan":0,"GiaMoCua":28.7,"GiaCaoNhat":28.7,"GiaThapNhat":28.3,"SoLenhMua":456,"KLDatMua":646500,"KLTB1LenhMua":1417.76,"SoLenhDatBan":541,"KLDatBan":592300,"KLTB1LenhBan":1095,"ChenhLechKL":"54,200","ThayDoi":"-0.3(-1.05 %)"},{"Date":"24\/10\/2024","GiaDieuChinh":28.4,"GiaDongCua":28.4,"KhoiLuongKhopLenh":514422,"GiaTriKhopLenh":14628750400,"KLThoaThuan":0,"GtThoaThuan":0,"GiaMoCua":28.4,"GiaCaoNhat":28.7,"GiaThapNhat":28.2,"SoLenhMua":460,"KLDatMua":697100,"KLTB1LenhMua":1515.43,"SoLenhDatBan":341,"KLDatBan":590300,"KLTB1LenhBan":1731,"ChenhLechKL":"106,800","ThayDoi":"0(0.00 %)"},{"Date":"08\/10\/2024","GiaDieuChinh":28.6,"GiaDongCua":28.6,"KhoiLuongKhopLenh":532121,"GiaTriKhopLenh":15126328600,"KLThoaThuan":0,"GtThoaThuan":0,"GiaMoCua":28.5,"GiaCaoNhat":28.7,"GiaThapNhat":28.2,"SoLenhMua":515,"KLDatMua":711700,"KLTB1LenhMua":1381.94,"SoLenhDatBan":383,"KLDatBan":596900,"KLTB1LenhBan":1558,"ChenhLechKL":"114,800","ThayDoi":"0.1(0.35 %)"},{"Date":"30\/09\/2024","GiaDieuChinh":28.5,"GiaDongCua":28.5,"KhoiLuongKhopLenh":544428,"GiaTriKhopLenh":15530383800,"KLThoaThuan":0,"GtThoaThuan":0,"GiaMoCua":28.9,"GiaCaoNhat":29.0,"GiaThapNhat":28.2,"SoLenhMua":360,"KLDatMua":700500,"KLTB1LenhMua":1945.83,"SoLenhDatBan":450,"KLDatBan":637700,"KLTB1LenhBan":1417,"ChenhLechKL":"62,800","ThayDoi":"-0.5(-1.72 %)"},{"Date":"04\/10\/2024","GiaDieuChinh":28.4,"GiaDongCua":28.4,"KhoiLuongKhopLenh":544925,"GiaTriKhopLenh":15395298100,"KLThoaThuan":0,"GtThoaThuan":0,"GiaMoCua":28.4,"GiaCaoNhat":28.5,"GiaThapNhat":28.0,"SoLenhMua":413,"KLDatMua":703300,"KLTB1LenhMua":1702.91,"SoLenhDatBan":430,"KLDatBan":587000,"KLTB1LenhBan":1365,"ChenhLechKL":"116,300","ThayDoi":"0(0.00 %)"},{"Date":"10\/10\/2024","GiaDieuChinh":28.9,"GiaDongCua":28.9,"KhoiLuongKhopLenh":562465,"GiaTriKhopLenh":16191662100,"KLThoaThuan":0,"GtThoaThuan":0,"GiaMoCua":28.8,"GiaCaoNhat":29.0,"GiaThapNhat":28.5,"SoLenhMua":523,"KLDatMua":729000,"KLTB1LenhMua":1393.88,"SoLenhDatBan":322,"KLDatBan":618600,"KLTB1LenhBan":1921,"ChenhLechKL":"110,400","ThayDoi":"0.1(0.35 %)"},{"Date":"21\/10\/2024","GiaDieuChinh":28.5,"GiaDongCua":28.5,"KhoiLuongKhopLenh":593108,"GiaTriKhopLenh":16927046400,"KLThoaThuan":0,"GtThoaThuan":0,"GiaMoCua":28.6,"GiaCaoNhat":28.9,"GiaThapNhat":28.4,"SoLenhMua":604,"KLDatMua":745400,"KLTB1LenhMua":1234.11,"SoLenhDatBan":491,"KLDatBan":667100,"KLTB1LenhBan":1359,"ChenhLechKL":"78,300","ThayDoi":"-0.1(-0.35 %)"},{"Date":"14\/10\/2024","GiaDieuChinh":29.0,"GiaDongCua":29.0,"KhoiLuongKhopLenh":594459,"GiaTriKhopLenh":17169631000,"KLThoaThuan":0,"GtThoaThuan":0,"GiaMoCua":29.0,"GiaCaoNhat":29.6,"GiaThapNhat":28.6,"SoLenhMua":557,"KLDatMua":768900,"KLTB1LenhMua":1380.43,"SoLenhDatBan":490,"KLDatBan":699500,"KLTB1LenhBan":1428,"ChenhLechKL":"69,400","ThayDoi":"0(0.00 %)"},{"Date":"11\/10\/2024","GiaDieuChinh":29.0,"GiaDongCua":29.0,"KhoiLuongKhopLenh":620934,"GiaTriKhopLenh":17886236000,"KLThoaThuan":0,"GtThoaThuan":0,"GiaMoCua":28.9,"GiaCaoNhat":29.5,"GiaThapNhat":28.6,"SoLenhMua":557,"KLDatMua":783700,"KLTB1LenhMua":1407.0,"SoLenhDatBan":389,"KLDatBan":690900,"KLTB1LenhBan":1776,"ChenhLechKL":"92,800","ThayDoi":"0.1(0.35 %)"},{"Date":"18\/10\/2024","GiaDieuChinh":28.6,"GiaDongCua":28.6,"KhoiLuongKhopLenh":625300,"GiaTriKhopLenh":17891690000,"KLThoaThuan":0,"GtThoaThuan":0,"GiaMoCua":28.8,"GiaCaoNhat":28.9,"GiaThapNhat":28.4,"SoLenhMua":717,"KLDatMua":790000,"KLTB1LenhMua":1101.81,"SoLenhDatBan":475,"KLDatBan":706600,"KLTB1LenhBan":1488,"ChenhLechKL":"83,400","ThayDoi":"-0.2(-0.69 %)"},{"Date":"25\/10\/2024","GiaDieuChinh":28.3,"GiaDongCua":28.3,"KhoiLuongKhopLenh":630700,"GiaTriKhopLenh":17932500000,"KLThoaThuan":0,"GtThoaThuan":0,"GiaMoCua":28.3,"GiaCaoNhat":28.7,"GiaThapNhat":28.2,"SoLenhMua":455,"KLDatMua":785400,"KLTB1LenhMua":1726.15,"SoLenhDatBan":488,"KLDatBan":711700,"KLTB1LenhBan":1458,"ChenhLechKL":"73,700","ThayDoi":"-0.1(-0.35 %)"},{"Date":"09\/10\/2024","GiaDieuChinh":28.8,"GiaDongCua":28.8,"KhoiLuongKhopLenh":639664,"GiaTriKhopLenh":18266757400,"KLThoaThuan":0,"GtThoaThuan":0,"GiaMoCua":28.6,"GiaCaoNhat":28.9,"GiaThapNhat":28.3,"SoLenhMua":530,"KLDatMua":808500,"KLTB1LenhMua":1525.47,"SoLenhDatBan":328,"KLDatBan":706700,"KLTB1LenhBan":2155,"ChenhLechKL":"101,800","ThayDoi":"0.2(0.70 %)"},{"Date":"16\/10\/2024","GiaDieuChinh":28.7,"GiaDongCua":28.7,"KhoiLuongKhopLenh":642508,"GiaTriKhopLenh":18355128800,"KLThoaThuan":343000,"GtThoaThuan":9809200000,"GiaMoCua":28.9,"GiaCaoNhat":28.9,"GiaThapNhat":28.3,"SoLenhMua":699,"KLDatMua":784500,"KLTB1LenhMua":1122.32,"SoLenhDatBan":521,"KLDatBan":731000,"KLTB1LenhBan":1403,"ChenhLechKL":"53,500","ThayDoi":"-0.2(-0.69 %)"},{"Date":"03\/10\/2024","GiaDieuChinh":28.4,"GiaDongCua":28.4,"KhoiLuongKhopLenh":643128,"GiaTriKhopLenh":18230661300,"KLThoaThuan":0,"GtThoaThuan":0,"GiaMoCua":28.4,"GiaCaoNhat":28.6,"GiaThapNhat":28.2,"SoLenhMua":403,"KLDatMua":803000,"KLTB1LenhMua":1992.56,"SoLenhDatBan":439,"KLDatBan":746900,"KLTB1LenhBan":1701,"ChenhLechKL":"56,100","ThayDoi":"0(0.00 %)"},{"Date":"23\/10\/2024","GiaDieuChinh":28.4,"GiaDongCua":28.4,"KhoiLuongKhopLenh":654700,"GiaTriKhopLenh":18565460000,"KLThoaThuan":0,"GtThoaThuan":0,"GiaMoCua":28.4,"GiaCaoNhat":28.6,"GiaThapNhat":28.1,"SoLenhMua":578,"KLDatMua":844700,"KLTB1LenhMua":1461.42,"SoLenhDatBan":595,"KLDatBan":730400,"KLTB1LenhBan":1228,"ChenhLechKL":"114,300","ThayDoi":"0(0.00 %)"},{"Date":"07\/10\/2024","GiaDieuChinh":28.5,"GiaDongCua":28.5,"KhoiLuongKhopLenh":660226,"GiaTriKhopLenh":18715788400,"KLThoaThuan":0,"GtThoaThuan":0,"GiaMoCua":28.3,"GiaCaoNhat":28.6,"GiaThapNhat":28.1,"SoLenhMua":498,"KLDatMua":824400,"KLTB1LenhMua":1655.42,"SoLenhDatBan":410,"KLDatBan":724500,"KLTB1LenhBan":1767,"ChenhLechKL":"99,900","ThayDoi":"0.1(0.35 %)"},{"Date":"17\/10\/2024","GiaDieuChinh":28.8,"GiaDongCua":28.8,"KhoiLuongKhopLenh":664010,"GiaTriKhopLenh":18844477000,"KLThoaThuan":0,"GtThoaThuan":0,"GiaMoCua":28.7,"GiaCaoNhat":28.8,"GiaThapNhat":28.0,"SoLenhMua":522,"KLDatMua":825400,"KLTB1LenhMua":1581.23,"SoLenhDatBan":554,"KLDatBan":717900,"KLTB1LenhBan":1296,"ChenhLechKL":"107,500","ThayDoi":"0.1(0.35 %)"},{"Date":"15\/10\/2024","GiaDieuChinh":28.9,"GiaDongCua":28.9,"KhoiLuongKhopLenh":677924,"GiaTriKhopLenh":19554546000,"KLThoaThuan":0,"GtThoaThuan":0,"GiaMoCua":29.0,"GiaCaoNhat":29.1,"GiaThapNhat":28.6,"SoLenhMua":638,"KLDatMua":832800,"KLTB1LenhMua":1305.33,"SoLenhDatBan":487,"KLDatBan":766000,"KLTB1LenhBan":1573,"ChenhLechKL":"66,800","ThayDoi":"-0.1(-0.34 %)"}]