[{"Date":"19\/03\/2024","GiaDieuChinh":4.36,"GiaDongCua":4.36,"KhoiLuongKhopLenh":540000.0,"GiaTriKhopLenh":2349000000.0,"KLThoaThuan":0.0,"GtThoaThuan":0.0,"GiaMoCua":4.38,"GiaCaoNhat":4.38,"GiaThapNhat":4.32,"SoLenhMua":294.0,"KLDatMua":2310400.0,"KLTB1LenhMua":7858.5,"SoLenhDatBan":351.0,"KLDatBan":1560100.0,"KLTB1LenhBan":4445.0,"ChenhLechKL":"750,300","ThayDoi":"0.05(1.16 %)"},{"Date":"20\/03\/2024","GiaDieuChinh":4.32,"GiaDongCua":4.32,"KhoiLuongKhopLenh":381800.0,"GiaTriKhopLenh":1655000000.0,"KLThoaThuan":0.0,"GtThoaThuan":0.0,"GiaMoCua":4.36,"GiaCaoNhat":4.36,"GiaThapNhat":4.31,"SoLenhMua":248.0,"KLDatMua":1445400.0,"KLTB1LenhMua":5828.23,"SoLenhDatBan":221.0,"KLDatBan":1430900.0,"KLTB1LenhBan":6475.0,"ChenhLechKL":"14,500","ThayDoi":"-0.04(-0.92 %)"},{"Date":"21\/03\/2024","GiaDieuChinh":4.39,"GiaDongCua":4.39,"KhoiLuongKhopLenh":673200.0,"GiaTriKhopLenh":2928000000.0,"KLThoaThuan":0.0,"GtThoaThuan":0.0,"GiaMoCua":4.32,"GiaCaoNhat":4.39,"GiaThapNhat":4.32,"SoLenhMua":371.0,"KLDatMua":2670000.0,"KLTB1LenhMua":7196.77,"SoLenhDatBan":380.0,"KLDatBan":1821800.0,"KLTB1LenhBan":4794.0,"ChenhLechKL":"848,200","ThayDoi":"0.07(1.62 %)"},{"Date":"22\/03\/2024","GiaDieuChinh":4.34,"GiaDongCua":4.34,"KhoiLuongKhopLenh":566200.0,"GiaTriKhopLenh":2471000000.0,"KLThoaThuan":0.0,"GtThoaThuan":0.0,"GiaMoCua":4.4,"GiaCaoNhat":4.44,"GiaThapNhat":4.33,"SoLenhMua":353.0,"KLDatMua":1388800.0,"KLTB1LenhMua":3934.28,"SoLenhDatBan":341.0,"KLDatBan":1884500.0,"KLTB1LenhBan":5526.0,"ChenhLechKL":"-495,700","ThayDoi":"-0.05(-1.14 %)"},{"Date":"25\/03\/2024","GiaDieuChinh":4.32,"GiaDongCua":4.32,"KhoiLuongKhopLenh":514200.0,"GiaTriKhopLenh":2238000000.0,"KLThoaThuan":0.0,"GtThoaThuan":0.0,"GiaMoCua":4.36,"GiaCaoNhat":4.4,"GiaThapNhat":4.32,"SoLenhMua":292.0,"KLDatMua":2158600.0,"KLTB1LenhMua":7392.47,"SoLenhDatBan":299.0,"KLDatBan":1617800.0,"KLTB1LenhBan":5411.0,"ChenhLechKL":"540,800","ThayDoi":"-0.02(-0.46 %)"},{"Date":"26\/03\/2024","GiaDieuChinh":4.45,"GiaDongCua":4.45,"KhoiLuongKhopLenh":998700.0,"GiaTriKhopLenh":4373000000.0,"KLThoaThuan":0.0,"GtThoaThuan":0.0,"GiaMoCua":4.29,"GiaCaoNhat":4.46,"GiaThapNhat":4.27,"SoLenhMua":483.0,"KLDatMua":2631100.0,"KLTB1LenhMua":5447.41,"SoLenhDatBan":477.0,"KLDatBan":2375400.0,"KLTB1LenhBan":4980.0,"ChenhLechKL":"255,700","ThayDoi":"0.13(3.01 %)"},{"Date":"27\/03\/2024","GiaDieuChinh":4.49,"GiaDongCua":4.49,"KhoiLuongKhopLenh":1031600.0,"GiaTriKhopLenh":4624000000.0,"KLThoaThuan":0.0,"GtThoaThuan":0.0,"GiaMoCua":4.45,"GiaCaoNhat":4.52,"GiaThapNhat":4.45,"SoLenhMua":700.0,"KLDatMua":1776800.0,"KLTB1LenhMua":2538.29,"SoLenhDatBan":554.0,"KLDatBan":2129500.0,"KLTB1LenhBan":3844.0,"ChenhLechKL":"-352,700","ThayDoi":"0.04(0.90 %)"},{"Date":"28\/03\/2024","GiaDieuChinh":4.47,"GiaDongCua":4.47,"KhoiLuongKhopLenh":635400.0,"GiaTriKhopLenh":2836000000.0,"KLThoaThuan":0.0,"GtThoaThuan":0.0,"GiaMoCua":4.58,"GiaCaoNhat":4.58,"GiaThapNhat":4.43,"SoLenhMua":534.0,"KLDatMua":1427300.0,"KLTB1LenhMua":2672.85,"SoLenhDatBan":304.0,"KLDatBan":2071000.0,"KLTB1LenhBan":6812.0,"ChenhLechKL":"-643,700","ThayDoi":"-0.02(-0.45 %)"},{"Date":"29\/03\/2024","GiaDieuChinh":4.4,"GiaDongCua":4.4,"KhoiLuongKhopLenh":336700.0,"GiaTriKhopLenh":1482000000.0,"KLThoaThuan":0.0,"GtThoaThuan":0.0,"GiaMoCua":4.41,"GiaCaoNhat":4.46,"GiaThapNhat":4.36,"SoLenhMua":408.0,"KLDatMua":840000.0,"KLTB1LenhMua":2058.82,"SoLenhDatBan":272.0,"KLDatBan":888400.0,"KLTB1LenhBan":3266.0,"ChenhLechKL":"-48,400","ThayDoi":"-0.07(-1.57 %)"},{"Date":"01\/04\/2024","GiaDieuChinh":4.51,"GiaDongCua":4.51,"KhoiLuongKhopLenh":854900.0,"GiaTriKhopLenh":3801000000.0,"KLThoaThuan":0.0,"GtThoaThuan":0.0,"GiaMoCua":4.4,"GiaCaoNhat":4.53,"GiaThapNhat":4.39,"SoLenhMua":460.0,"KLDatMua":1675000.0,"KLTB1LenhMua":3641.3,"SoLenhDatBan":445.0,"KLDatBan":1579300.0,"KLTB1LenhBan":3549.0,"ChenhLechKL":"95,700","ThayDoi":"0.11(2.50 %)"},{"Date":"02\/04\/2024","GiaDieuChinh":4.48,"GiaDongCua":4.48,"KhoiLuongKhopLenh":603600.0,"GiaTriKhopLenh":2702000000.0,"KLThoaThuan":0.0,"GtThoaThuan":0.0,"GiaMoCua":4.47,"GiaCaoNhat":4.51,"GiaThapNhat":4.45,"SoLenhMua":464.0,"KLDatMua":1145800.0,"KLTB1LenhMua":2469.4,"SoLenhDatBan":381.0,"KLDatBan":1345700.0,"KLTB1LenhBan":3532.0,"ChenhLechKL":"-199,900","ThayDoi":"-0.03(-0.67 %)"},{"Date":"03\/04\/2024","GiaDieuChinh":4.48,"GiaDongCua":4.48,"KhoiLuongKhopLenh":672400.0,"GiaTriKhopLenh":3022000000.0,"KLThoaThuan":0.0,"GtThoaThuan":0.0,"GiaMoCua":4.48,"GiaCaoNhat":4.54,"GiaThapNhat":4.41,"SoLenhMua":459.0,"KLDatMua":1568000.0,"KLTB1LenhMua":3416.12,"SoLenhDatBan":453.0,"KLDatBan":1723000.0,"KLTB1LenhBan":3804.0,"ChenhLechKL":"-155,000","ThayDoi":"0(0.00 %)"},{"Date":"04\/04\/2024","GiaDieuChinh":4.7,"GiaDongCua":4.7,"KhoiLuongKhopLenh":1619700.0,"GiaTriKhopLenh":7517000000.0,"KLThoaThuan":0.0,"GtThoaThuan":0.0,"GiaMoCua":4.52,"GiaCaoNhat":4.73,"GiaThapNhat":4.49,"SoLenhMua":832.0,"KLDatMua":2967900.0,"KLTB1LenhMua":3567.19,"SoLenhDatBan":913.0,"KLDatBan":3541100.0,"KLTB1LenhBan":3879.0,"ChenhLechKL":"-573,200","ThayDoi":"0.22(4.91 %)"},{"Date":"05\/04\/2024","GiaDieuChinh":4.91,"GiaDongCua":4.91,"KhoiLuongKhopLenh":3331100.0,"GiaTriKhopLenh":16474000000.0,"KLThoaThuan":0.0,"GtThoaThuan":0.0,"GiaMoCua":4.5,"GiaCaoNhat":5.02,"GiaThapNhat":4.46,"SoLenhMua":1251.0,"KLDatMua":6909800.0,"KLTB1LenhMua":5523.42,"SoLenhDatBan":1050.0,"KLDatBan":5560800.0,"KLTB1LenhBan":5296.0,"ChenhLechKL":"1,349,000","ThayDoi":"0.21(4.47 %)"},{"Date":"08\/04\/2024","GiaDieuChinh":4.75,"GiaDongCua":4.75,"KhoiLuongKhopLenh":1146800.0,"GiaTriKhopLenh":5530000000.0,"KLThoaThuan":0.0,"GtThoaThuan":0.0,"GiaMoCua":4.93,"GiaCaoNhat":4.95,"GiaThapNhat":4.7,"SoLenhMua":621.0,"KLDatMua":2662900.0,"KLTB1LenhMua":4288.08,"SoLenhDatBan":614.0,"KLDatBan":2827300.0,"KLTB1LenhBan":4605.0,"ChenhLechKL":"-164,400","ThayDoi":"-0.16(-3.26 %)"},{"Date":"09\/04\/2024","GiaDieuChinh":4.67,"GiaDongCua":4.67,"KhoiLuongKhopLenh":846000.0,"GiaTriKhopLenh":3975000000.0,"KLThoaThuan":0.0,"GtThoaThuan":0.0,"GiaMoCua":4.8,"GiaCaoNhat":4.82,"GiaThapNhat":4.62,"SoLenhMua":649.0,"KLDatMua":1548700.0,"KLTB1LenhMua":2386.29,"SoLenhDatBan":541.0,"KLDatBan":1778400.0,"KLTB1LenhBan":3287.0,"ChenhLechKL":"-229,700","ThayDoi":"-0.08(-1.68 %)"},{"Date":"10\/04\/2024","GiaDieuChinh":4.6,"GiaDongCua":4.6,"KhoiLuongKhopLenh":800100.0,"GiaTriKhopLenh":3735000000.0,"KLThoaThuan":0.0,"GtThoaThuan":0.0,"GiaMoCua":4.74,"GiaCaoNhat":4.77,"GiaThapNhat":4.6,"SoLenhMua":617.0,"KLDatMua":1784600.0,"KLTB1LenhMua":2892.38,"SoLenhDatBan":302.0,"KLDatBan":1582700.0,"KLTB1LenhBan":5241.0,"ChenhLechKL":"201,900","ThayDoi":"-0.07(-1.50 %)"},{"Date":"11\/04\/2024","GiaDieuChinh":4.54,"GiaDongCua":4.54,"KhoiLuongKhopLenh":879300.0,"GiaTriKhopLenh":3971000000.0,"KLThoaThuan":0.0,"GtThoaThuan":0.0,"GiaMoCua":4.51,"GiaCaoNhat":4.57,"GiaThapNhat":4.5,"SoLenhMua":null,"KLDatMua":null,"KLTB1LenhMua":null,"SoLenhDatBan":null,"KLDatBan":null,"KLTB1LenhBan":null,"ChenhLechKL":null,"ThayDoi":"-0.06(-1.30 %)"},{"Date":"12\/04\/2024","GiaDieuChinh":4.51,"GiaDongCua":4.51,"KhoiLuongKhopLenh":932300.0,"GiaTriKhopLenh":4203000000.0,"KLThoaThuan":0.0,"GtThoaThuan":0.0,"GiaMoCua":4.65,"GiaCaoNhat":4.65,"GiaThapNhat":4.46,"SoLenhMua":null,"KLDatMua":null,"KLTB1LenhMua":null,"SoLenhDatBan":null,"KLDatBan":null,"KLTB1LenhBan":null,"ChenhLechKL":null,"ThayDoi":"-0.03(-0.66 %)"},{"Date":"15\/04\/2024","GiaDieuChinh":4.22,"GiaDongCua":4.22,"KhoiLuongKhopLenh":1044500.0,"GiaTriKhopLenh":4604000000.0,"KLThoaThuan":0.0,"GtThoaThuan":0.0,"GiaMoCua":4.5,"GiaCaoNhat":4.59,"GiaThapNhat":4.21,"SoLenhMua":null,"KLDatMua":null,"KLTB1LenhMua":null,"SoLenhDatBan":null,"KLDatBan":null,"KLTB1LenhBan":null,"ChenhLechKL":null,"ThayDoi":"-0.29(-6.43 %)"},{"Date":"14\/03\/2024","GiaDieuChinh":null,"GiaDongCua":null,"KhoiLuongKhopLenh":null,"GiaTriKhopLenh":null,"KLThoaThuan":null,"GtThoaThuan":null,"GiaMoCua":null,"GiaCaoNhat":null,"GiaThapNhat":null,"SoLenhMua":339.0,"KLDatMua":2040800.0,"KLTB1LenhMua":6020.06,"SoLenhDatBan":310.0,"KLDatBan":1758000.0,"KLTB1LenhBan":5671.0,"ChenhLechKL":"282,800","ThayDoi":null},{"Date":"15\/03\/2024","GiaDieuChinh":null,"GiaDongCua":null,"KhoiLuongKhopLenh":null,"GiaTriKhopLenh":null,"KLThoaThuan":null,"GtThoaThuan":null,"GiaMoCua":null,"GiaCaoNhat":null,"GiaThapNhat":null,"SoLenhMua":253.0,"KLDatMua":1580800.0,"KLTB1LenhMua":6248.22,"SoLenhDatBan":309.0,"KLDatBan":1080100.0,"KLTB1LenhBan":3495.0,"ChenhLechKL":"500,700","ThayDoi":null},{"Date":"18\/03\/2024","GiaDieuChinh":null,"GiaDongCua":null,"KhoiLuongKhopLenh":null,"GiaTriKhopLenh":null,"KLThoaThuan":null,"GtThoaThuan":null,"GiaMoCua":null,"GiaCaoNhat":null,"GiaThapNhat":null,"SoLenhMua":463.0,"KLDatMua":1897500.0,"KLTB1LenhMua":4098.27,"SoLenhDatBan":548.0,"KLDatBan":2244300.0,"KLTB1LenhBan":4095.0,"ChenhLechKL":"-346,800","ThayDoi":null}]