[{"Date":"17\/06\/2024","GiaDieuChinh":32.76,"GiaDongCua":35.8,"KhoiLuongKhopLenh":19800.0,"GiaTriKhopLenh":708000000.0,"KLThoaThuan":0.0,"GtThoaThuan":0.0,"GiaMoCua":35.85,"GiaCaoNhat":35.95,"GiaThapNhat":35.7,"SoLenhMua":50.0,"KLDatMua":53500.0,"KLTB1LenhMua":1070.0,"SoLenhDatBan":48.0,"KLDatBan":58300.0,"KLTB1LenhBan":1215.0,"ChenhLechKL":"-4,800","ThayDoi":"0.1(0.28 %)"},{"Date":"18\/06\/2024","GiaDieuChinh":32.86,"GiaDongCua":35.9,"KhoiLuongKhopLenh":33700.0,"GiaTriKhopLenh":1211000000.0,"KLThoaThuan":0.0,"GtThoaThuan":0.0,"GiaMoCua":36.0,"GiaCaoNhat":36.05,"GiaThapNhat":35.65,"SoLenhMua":53.0,"KLDatMua":55900.0,"KLTB1LenhMua":1054.72,"SoLenhDatBan":47.0,"KLDatBan":79900.0,"KLTB1LenhBan":1700.0,"ChenhLechKL":"-24,000","ThayDoi":"0.1(0.28 %)"},{"Date":"19\/06\/2024","GiaDieuChinh":32.81,"GiaDongCua":35.85,"KhoiLuongKhopLenh":8500.0,"GiaTriKhopLenh":305000000.0,"KLThoaThuan":0.0,"GtThoaThuan":0.0,"GiaMoCua":36.0,"GiaCaoNhat":36.0,"GiaThapNhat":35.6,"SoLenhMua":51.0,"KLDatMua":54800.0,"KLTB1LenhMua":1074.51,"SoLenhDatBan":35.0,"KLDatBan":40400.0,"KLTB1LenhBan":1154.0,"ChenhLechKL":"14,400","ThayDoi":"-0.05(-0.14 %)"},{"Date":"21\/06\/2024","GiaDieuChinh":32.9,"GiaDongCua":35.95,"KhoiLuongKhopLenh":30300.0,"GiaTriKhopLenh":1092000000.0,"KLThoaThuan":0.0,"GtThoaThuan":0.0,"GiaMoCua":35.9,"GiaCaoNhat":36.2,"GiaThapNhat":35.7,"SoLenhMua":63.0,"KLDatMua":63000.0,"KLTB1LenhMua":1000.0,"SoLenhDatBan":46.0,"KLDatBan":48300.0,"KLTB1LenhBan":1050.0,"ChenhLechKL":"14,700","ThayDoi":"0.05(0.14 %)"},{"Date":"25\/06\/2024","GiaDieuChinh":32.95,"GiaDongCua":36.0,"KhoiLuongKhopLenh":74100.0,"GiaTriKhopLenh":2644000000.0,"KLThoaThuan":0.0,"GtThoaThuan":0.0,"GiaMoCua":36.2,"GiaCaoNhat":36.2,"GiaThapNhat":35.2,"SoLenhMua":104.0,"KLDatMua":223700.0,"KLTB1LenhMua":2150.96,"SoLenhDatBan":68.0,"KLDatBan":97500.0,"KLTB1LenhBan":1434.0,"ChenhLechKL":"126,200","ThayDoi":"-0.05(-0.14 %)"},{"Date":"26\/06\/2024","GiaDieuChinh":33.22,"GiaDongCua":36.3,"KhoiLuongKhopLenh":23100.0,"GiaTriKhopLenh":835000000.0,"KLThoaThuan":0.0,"GtThoaThuan":0.0,"GiaMoCua":36.3,"GiaCaoNhat":36.3,"GiaThapNhat":35.5,"SoLenhMua":61.0,"KLDatMua":94400.0,"KLTB1LenhMua":1547.54,"SoLenhDatBan":39.0,"KLDatBan":44900.0,"KLTB1LenhBan":1151.0,"ChenhLechKL":"49,500","ThayDoi":"0.3(0.83 %)"},{"Date":"27\/06\/2024","GiaDieuChinh":33.22,"GiaDongCua":35.3,"KhoiLuongKhopLenh":12600.0,"GiaTriKhopLenh":444000000.0,"KLThoaThuan":0.0,"GtThoaThuan":0.0,"GiaMoCua":35.1,"GiaCaoNhat":35.3,"GiaThapNhat":35.1,"SoLenhMua":76.0,"KLDatMua":88400.0,"KLTB1LenhMua":1163.16,"SoLenhDatBan":42.0,"KLDatBan":57800.0,"KLTB1LenhBan":1376.0,"ChenhLechKL":"30,600","ThayDoi":"0(0.00 %)"},{"Date":"28\/06\/2024","GiaDieuChinh":32.94,"GiaDongCua":35.0,"KhoiLuongKhopLenh":31200.0,"GiaTriKhopLenh":1093000000.0,"KLThoaThuan":0.0,"GtThoaThuan":0.0,"GiaMoCua":35.45,"GiaCaoNhat":35.45,"GiaThapNhat":34.9,"SoLenhMua":66.0,"KLDatMua":82900.0,"KLTB1LenhMua":1256.06,"SoLenhDatBan":42.0,"KLDatBan":100900.0,"KLTB1LenhBan":2402.0,"ChenhLechKL":"-18,000","ThayDoi":"-0.3(-0.85 %)"},{"Date":"01\/07\/2024","GiaDieuChinh":32.94,"GiaDongCua":35.0,"KhoiLuongKhopLenh":95400.0,"GiaTriKhopLenh":3301000000.0,"KLThoaThuan":0.0,"GtThoaThuan":0.0,"GiaMoCua":35.0,"GiaCaoNhat":35.2,"GiaThapNhat":34.5,"SoLenhMua":74.0,"KLDatMua":221500.0,"KLTB1LenhMua":2993.24,"SoLenhDatBan":43.0,"KLDatBan":151800.0,"KLTB1LenhBan":3530.0,"ChenhLechKL":"69,700","ThayDoi":"0(0.00 %)"},{"Date":"02\/07\/2024","GiaDieuChinh":33.08,"GiaDongCua":35.15,"KhoiLuongKhopLenh":33400.0,"GiaTriKhopLenh":1174000000.0,"KLThoaThuan":0.0,"GtThoaThuan":0.0,"GiaMoCua":35.65,"GiaCaoNhat":35.65,"GiaThapNhat":35.0,"SoLenhMua":67.0,"KLDatMua":198400.0,"KLTB1LenhMua":2961.19,"SoLenhDatBan":48.0,"KLDatBan":88200.0,"KLTB1LenhBan":1838.0,"ChenhLechKL":"110,200","ThayDoi":"0.15(0.43 %)"},{"Date":"03\/07\/2024","GiaDieuChinh":33.83,"GiaDongCua":35.95,"KhoiLuongKhopLenh":44600.0,"GiaTriKhopLenh":1581000000.0,"KLThoaThuan":0.0,"GtThoaThuan":0.0,"GiaMoCua":35.05,"GiaCaoNhat":36.0,"GiaThapNhat":35.05,"SoLenhMua":65.0,"KLDatMua":359900.0,"KLTB1LenhMua":5536.92,"SoLenhDatBan":52.0,"KLDatBan":90600.0,"KLTB1LenhBan":1742.0,"ChenhLechKL":"269,300","ThayDoi":"0.8(2.28 %)"},{"Date":"04\/07\/2024","GiaDieuChinh":34.35,"GiaDongCua":36.5,"KhoiLuongKhopLenh":40000.0,"GiaTriKhopLenh":1459000000.0,"KLThoaThuan":0.0,"GtThoaThuan":0.0,"GiaMoCua":35.5,"GiaCaoNhat":37.5,"GiaThapNhat":35.5,"SoLenhMua":119.0,"KLDatMua":207000.0,"KLTB1LenhMua":1739.5,"SoLenhDatBan":89.0,"KLDatBan":149600.0,"KLTB1LenhBan":1681.0,"ChenhLechKL":"57,400","ThayDoi":"0.55(1.53 %)"},{"Date":"05\/07\/2024","GiaDieuChinh":34.26,"GiaDongCua":36.4,"KhoiLuongKhopLenh":34400.0,"GiaTriKhopLenh":1254000000.0,"KLThoaThuan":0.0,"GtThoaThuan":0.0,"GiaMoCua":37.65,"GiaCaoNhat":37.65,"GiaThapNhat":36.1,"SoLenhMua":90.0,"KLDatMua":232700.0,"KLTB1LenhMua":2585.56,"SoLenhDatBan":78.0,"KLDatBan":197800.0,"KLTB1LenhBan":2536.0,"ChenhLechKL":"34,900","ThayDoi":"-0.1(-0.27 %)"},{"Date":"08\/07\/2024","GiaDieuChinh":35.29,"GiaDongCua":37.5,"KhoiLuongKhopLenh":78900.0,"GiaTriKhopLenh":2917000000.0,"KLThoaThuan":0.0,"GtThoaThuan":0.0,"GiaMoCua":36.5,"GiaCaoNhat":37.9,"GiaThapNhat":36.4,"SoLenhMua":90.0,"KLDatMua":242800.0,"KLTB1LenhMua":2697.78,"SoLenhDatBan":101.0,"KLDatBan":174700.0,"KLTB1LenhBan":1730.0,"ChenhLechKL":"68,100","ThayDoi":"1.1(3.02 %)"},{"Date":"09\/07\/2024","GiaDieuChinh":35.48,"GiaDongCua":37.7,"KhoiLuongKhopLenh":34400.0,"GiaTriKhopLenh":1296000000.0,"KLThoaThuan":0.0,"GtThoaThuan":0.0,"GiaMoCua":36.9,"GiaCaoNhat":38.3,"GiaThapNhat":36.9,"SoLenhMua":148.0,"KLDatMua":168200.0,"KLTB1LenhMua":1136.49,"SoLenhDatBan":87.0,"KLDatBan":110600.0,"KLTB1LenhBan":1271.0,"ChenhLechKL":"57,600","ThayDoi":"0.2(0.53 %)"},{"Date":"10\/07\/2024","GiaDieuChinh":35.76,"GiaDongCua":38.0,"KhoiLuongKhopLenh":3400.0,"GiaTriKhopLenh":128000000.0,"KLThoaThuan":0.0,"GtThoaThuan":0.0,"GiaMoCua":38.1,"GiaCaoNhat":38.1,"GiaThapNhat":37.8,"SoLenhMua":null,"KLDatMua":null,"KLTB1LenhMua":null,"SoLenhDatBan":null,"KLDatBan":null,"KLTB1LenhBan":null,"ChenhLechKL":null,"ThayDoi":"0.3(0.80 %)"},{"Date":"11\/07\/2024","GiaDieuChinh":35.62,"GiaDongCua":37.85,"KhoiLuongKhopLenh":57000.0,"GiaTriKhopLenh":2159000000.0,"KLThoaThuan":0.0,"GtThoaThuan":0.0,"GiaMoCua":37.9,"GiaCaoNhat":38.4,"GiaThapNhat":37.2,"SoLenhMua":null,"KLDatMua":null,"KLTB1LenhMua":null,"SoLenhDatBan":null,"KLDatBan":null,"KLTB1LenhBan":null,"ChenhLechKL":null,"ThayDoi":"-0.15(-0.39 %)"},{"Date":"12\/07\/2024","GiaDieuChinh":35.57,"GiaDongCua":37.8,"KhoiLuongKhopLenh":12600.0,"GiaTriKhopLenh":476000000.0,"KLThoaThuan":0.0,"GtThoaThuan":0.0,"GiaMoCua":37.9,"GiaCaoNhat":38.0,"GiaThapNhat":37.8,"SoLenhMua":null,"KLDatMua":null,"KLTB1LenhMua":null,"SoLenhDatBan":null,"KLDatBan":null,"KLTB1LenhBan":null,"ChenhLechKL":null,"ThayDoi":"-0.05(-0.13 %)"},{"Date":"20\/06\/2024","GiaDieuChinh":32.86,"GiaDongCua":35.9,"KhoiLuongKhopLenh":22300.0,"GiaTriKhopLenh":797000000.0,"KLThoaThuan":20000.0,"GtThoaThuan":718000000.0,"GiaMoCua":36.0,"GiaCaoNhat":36.0,"GiaThapNhat":35.6,"SoLenhMua":49.0,"KLDatMua":43400.0,"KLTB1LenhMua":885.71,"SoLenhDatBan":36.0,"KLDatBan":50100.0,"KLTB1LenhBan":1392.0,"ChenhLechKL":"-6,700","ThayDoi":"0.05(0.14 %)"},{"Date":"24\/06\/2024","GiaDieuChinh":32.99,"GiaDongCua":36.05,"KhoiLuongKhopLenh":25700.0,"GiaTriKhopLenh":925000000.0,"KLThoaThuan":20000.0,"GtThoaThuan":718000000.0,"GiaMoCua":35.95,"GiaCaoNhat":36.2,"GiaThapNhat":35.7,"SoLenhMua":68.0,"KLDatMua":67500.0,"KLTB1LenhMua":992.65,"SoLenhDatBan":63.0,"KLDatBan":68900.0,"KLTB1LenhBan":1094.0,"ChenhLechKL":"-1,400","ThayDoi":"0.1(0.28 %)"},{"Date":"12\/06\/2024","GiaDieuChinh":null,"GiaDongCua":null,"KhoiLuongKhopLenh":null,"GiaTriKhopLenh":null,"KLThoaThuan":null,"GtThoaThuan":null,"GiaMoCua":null,"GiaCaoNhat":null,"GiaThapNhat":null,"SoLenhMua":101.0,"KLDatMua":128300.0,"KLTB1LenhMua":1270.3,"SoLenhDatBan":76.0,"KLDatBan":81800.0,"KLTB1LenhBan":1076.0,"ChenhLechKL":"46,500","ThayDoi":null},{"Date":"13\/06\/2024","GiaDieuChinh":null,"GiaDongCua":null,"KhoiLuongKhopLenh":null,"GiaTriKhopLenh":null,"KLThoaThuan":null,"GtThoaThuan":null,"GiaMoCua":null,"GiaCaoNhat":null,"GiaThapNhat":null,"SoLenhMua":63.0,"KLDatMua":74600.0,"KLTB1LenhMua":1184.13,"SoLenhDatBan":86.0,"KLDatBan":71500.0,"KLTB1LenhBan":831.0,"ChenhLechKL":"3,100","ThayDoi":null},{"Date":"14\/06\/2024","GiaDieuChinh":null,"GiaDongCua":null,"KhoiLuongKhopLenh":null,"GiaTriKhopLenh":null,"KLThoaThuan":null,"GtThoaThuan":null,"GiaMoCua":null,"GiaCaoNhat":null,"GiaThapNhat":null,"SoLenhMua":57.0,"KLDatMua":60600.0,"KLTB1LenhMua":1063.16,"SoLenhDatBan":64.0,"KLDatBan":90600.0,"KLTB1LenhBan":1416.0,"ChenhLechKL":"-30,000","ThayDoi":null}]