[{"Date":"25\/10\/2024","GiaDieuChinh":2.54,"GiaDongCua":2.54,"KhoiLuongKhopLenh":53300.0,"GiaTriKhopLenh":137000000.0,"KLThoaThuan":0.0,"GtThoaThuan":0.0,"GiaMoCua":2.69,"GiaCaoNhat":2.69,"GiaThapNhat":2.54,"SoLenhMua":66.0,"KLDatMua":138900.0,"KLTB1LenhMua":2104.55,"SoLenhDatBan":46.0,"KLDatBan":129300.0,"KLTB1LenhBan":2811.0,"ChenhLechKL":"9,600","ThayDoi":"-0.06(-2.31 %)"},{"Date":"23\/10\/2024","GiaDieuChinh":2.58,"GiaDongCua":2.58,"KhoiLuongKhopLenh":26200.0,"GiaTriKhopLenh":70000000.0,"KLThoaThuan":0.0,"GtThoaThuan":0.0,"GiaMoCua":2.77,"GiaCaoNhat":2.77,"GiaThapNhat":2.58,"SoLenhMua":58.0,"KLDatMua":42300.0,"KLTB1LenhMua":729.31,"SoLenhDatBan":26.0,"KLDatBan":73700.0,"KLTB1LenhBan":2835.0,"ChenhLechKL":"-31,400","ThayDoi":"-0.19(-6.86 %)"},{"Date":"24\/10\/2024","GiaDieuChinh":2.6,"GiaDongCua":2.6,"KhoiLuongKhopLenh":78400.0,"GiaTriKhopLenh":202000000.0,"KLThoaThuan":0.0,"GtThoaThuan":0.0,"GiaMoCua":2.53,"GiaCaoNhat":2.68,"GiaThapNhat":2.53,"SoLenhMua":110.0,"KLDatMua":282900.0,"KLTB1LenhMua":2571.82,"SoLenhDatBan":55.0,"KLDatBan":137000.0,"KLTB1LenhBan":2491.0,"ChenhLechKL":"145,900","ThayDoi":"0.02(0.78 %)"},{"Date":"28\/10\/2024","GiaDieuChinh":2.71,"GiaDongCua":2.71,"KhoiLuongKhopLenh":58700.0,"GiaTriKhopLenh":158000000.0,"KLThoaThuan":0.0,"GtThoaThuan":0.0,"GiaMoCua":2.54,"GiaCaoNhat":2.71,"GiaThapNhat":2.54,"SoLenhMua":122.0,"KLDatMua":877900.0,"KLTB1LenhMua":7195.9,"SoLenhDatBan":43.0,"KLDatBan":66400.0,"KLTB1LenhBan":1544.0,"ChenhLechKL":"811,500","ThayDoi":"0.17(6.69 %)"},{"Date":"05\/11\/2024","GiaDieuChinh":2.76,"GiaDongCua":2.76,"KhoiLuongKhopLenh":24700.0,"GiaTriKhopLenh":68000000.0,"KLThoaThuan":0.0,"GtThoaThuan":0.0,"GiaMoCua":2.8,"GiaCaoNhat":2.82,"GiaThapNhat":2.76,"SoLenhMua":null,"KLDatMua":null,"KLTB1LenhMua":null,"SoLenhDatBan":null,"KLDatBan":null,"KLTB1LenhBan":null,"ChenhLechKL":null,"ThayDoi":"-0.08(-2.82 %)"},{"Date":"22\/10\/2024","GiaDieuChinh":2.77,"GiaDongCua":2.77,"KhoiLuongKhopLenh":26000.0,"GiaTriKhopLenh":71000000.0,"KLThoaThuan":0.0,"GtThoaThuan":0.0,"GiaMoCua":2.77,"GiaCaoNhat":2.79,"GiaThapNhat":2.75,"SoLenhMua":52.0,"KLDatMua":47200.0,"KLTB1LenhMua":907.69,"SoLenhDatBan":36.0,"KLDatBan":169400.0,"KLTB1LenhBan":4706.0,"ChenhLechKL":"-122,200","ThayDoi":"0(0.00 %)"},{"Date":"21\/10\/2024","GiaDieuChinh":2.77,"GiaDongCua":2.77,"KhoiLuongKhopLenh":29100.0,"GiaTriKhopLenh":81000000.0,"KLThoaThuan":0.0,"GtThoaThuan":0.0,"GiaMoCua":2.81,"GiaCaoNhat":2.81,"GiaThapNhat":2.77,"SoLenhMua":53.0,"KLDatMua":88900.0,"KLTB1LenhMua":1677.36,"SoLenhDatBan":32.0,"KLDatBan":200800.0,"KLTB1LenhBan":6275.0,"ChenhLechKL":"-111,900","ThayDoi":"-0.08(-2.81 %)"},{"Date":"15\/10\/2024","GiaDieuChinh":2.8,"GiaDongCua":2.8,"KhoiLuongKhopLenh":79900.0,"GiaTriKhopLenh":223000000.0,"KLThoaThuan":0.0,"GtThoaThuan":0.0,"GiaMoCua":2.82,"GiaCaoNhat":2.83,"GiaThapNhat":2.78,"SoLenhMua":79.0,"KLDatMua":131300.0,"KLTB1LenhMua":1662.03,"SoLenhDatBan":61.0,"KLDatBan":158400.0,"KLTB1LenhBan":2597.0,"ChenhLechKL":"-27,100","ThayDoi":"-0.02(-0.71 %)"},{"Date":"14\/10\/2024","GiaDieuChinh":2.82,"GiaDongCua":2.82,"KhoiLuongKhopLenh":41700.0,"GiaTriKhopLenh":117000000.0,"KLThoaThuan":0.0,"GtThoaThuan":0.0,"GiaMoCua":2.93,"GiaCaoNhat":2.95,"GiaThapNhat":2.75,"SoLenhMua":68.0,"KLDatMua":93000.0,"KLTB1LenhMua":1367.65,"SoLenhDatBan":61.0,"KLDatBan":133400.0,"KLTB1LenhBan":2187.0,"ChenhLechKL":"-40,400","ThayDoi":"-0.08(-2.76 %)"},{"Date":"04\/11\/2024","GiaDieuChinh":2.84,"GiaDongCua":2.84,"KhoiLuongKhopLenh":46900.0,"GiaTriKhopLenh":130000000.0,"KLThoaThuan":0.0,"GtThoaThuan":0.0,"GiaMoCua":2.74,"GiaCaoNhat":2.88,"GiaThapNhat":2.71,"SoLenhMua":92.0,"KLDatMua":102500.0,"KLTB1LenhMua":1114.13,"SoLenhDatBan":63.0,"KLDatBan":124000.0,"KLTB1LenhBan":1968.0,"ChenhLechKL":"-21,500","ThayDoi":"-0.07(-2.41 %)"},{"Date":"18\/10\/2024","GiaDieuChinh":2.85,"GiaDongCua":2.85,"KhoiLuongKhopLenh":68300.0,"GiaTriKhopLenh":193000000.0,"KLThoaThuan":0.0,"GtThoaThuan":0.0,"GiaMoCua":2.83,"GiaCaoNhat":2.89,"GiaThapNhat":2.82,"SoLenhMua":53.0,"KLDatMua":99800.0,"KLTB1LenhMua":1883.02,"SoLenhDatBan":55.0,"KLDatBan":178900.0,"KLTB1LenhBan":3253.0,"ChenhLechKL":"-79,100","ThayDoi":"-0.05(-1.72 %)"},{"Date":"16\/10\/2024","GiaDieuChinh":2.88,"GiaDongCua":2.88,"KhoiLuongKhopLenh":62500.0,"GiaTriKhopLenh":177000000.0,"KLThoaThuan":0.0,"GtThoaThuan":0.0,"GiaMoCua":2.89,"GiaCaoNhat":2.89,"GiaThapNhat":2.79,"SoLenhMua":54.0,"KLDatMua":112000.0,"KLTB1LenhMua":2074.07,"SoLenhDatBan":70.0,"KLDatBan":168100.0,"KLTB1LenhBan":2401.0,"ChenhLechKL":"-56,100","ThayDoi":"0.08(2.86 %)"},{"Date":"09\/10\/2024","GiaDieuChinh":2.88,"GiaDongCua":2.88,"KhoiLuongKhopLenh":177000.0,"GiaTriKhopLenh":505000000.0,"KLThoaThuan":0.0,"GtThoaThuan":0.0,"GiaMoCua":2.82,"GiaCaoNhat":2.92,"GiaThapNhat":2.8,"SoLenhMua":121.0,"KLDatMua":276600.0,"KLTB1LenhMua":2285.95,"SoLenhDatBan":99.0,"KLDatBan":233500.0,"KLTB1LenhBan":2359.0,"ChenhLechKL":"43,100","ThayDoi":"0.06(2.13 %)"},{"Date":"30\/10\/2024","GiaDieuChinh":2.89,"GiaDongCua":2.89,"KhoiLuongKhopLenh":270000.0,"GiaTriKhopLenh":822000000.0,"KLThoaThuan":0.0,"GtThoaThuan":0.0,"GiaMoCua":3.09,"GiaCaoNhat":3.09,"GiaThapNhat":2.8,"SoLenhMua":196.0,"KLDatMua":1279400.0,"KLTB1LenhMua":6527.55,"SoLenhDatBan":150.0,"KLDatBan":428200.0,"KLTB1LenhBan":2855.0,"ChenhLechKL":"851,200","ThayDoi":"0(0.00 %)"},{"Date":"29\/10\/2024","GiaDieuChinh":2.89,"GiaDongCua":2.89,"KhoiLuongKhopLenh":33400.0,"GiaTriKhopLenh":96000000.0,"KLThoaThuan":0.0,"GtThoaThuan":0.0,"GiaMoCua":2.89,"GiaCaoNhat":2.89,"GiaThapNhat":2.89,"SoLenhMua":81.0,"KLDatMua":975800.0,"KLTB1LenhMua":12046.91,"SoLenhDatBan":19.0,"KLDatBan":33400.0,"KLTB1LenhBan":1758.0,"ChenhLechKL":"942,400","ThayDoi":"0.18(6.64 %)"},{"Date":"17\/10\/2024","GiaDieuChinh":2.9,"GiaDongCua":2.9,"KhoiLuongKhopLenh":36500.0,"GiaTriKhopLenh":104000000.0,"KLThoaThuan":0.0,"GtThoaThuan":0.0,"GiaMoCua":2.85,"GiaCaoNhat":2.9,"GiaThapNhat":2.81,"SoLenhMua":58.0,"KLDatMua":92000.0,"KLTB1LenhMua":1586.21,"SoLenhDatBan":42.0,"KLDatBan":92900.0,"KLTB1LenhBan":2212.0,"ChenhLechKL":"-900","ThayDoi":"0.02(0.69 %)"},{"Date":"11\/10\/2024","GiaDieuChinh":2.9,"GiaDongCua":2.9,"KhoiLuongKhopLenh":4500.0,"GiaTriKhopLenh":12000000.0,"KLThoaThuan":0.0,"GtThoaThuan":0.0,"GiaMoCua":2.83,"GiaCaoNhat":2.9,"GiaThapNhat":2.83,"SoLenhMua":49.0,"KLDatMua":69300.0,"KLTB1LenhMua":1414.29,"SoLenhDatBan":32.0,"KLDatBan":37200.0,"KLTB1LenhBan":1162.0,"ChenhLechKL":"32,100","ThayDoi":"0(0.00 %)"},{"Date":"10\/10\/2024","GiaDieuChinh":2.9,"GiaDongCua":2.9,"KhoiLuongKhopLenh":30400.0,"GiaTriKhopLenh":88000000.0,"KLThoaThuan":0.0,"GtThoaThuan":0.0,"GiaMoCua":2.9,"GiaCaoNhat":2.94,"GiaThapNhat":2.85,"SoLenhMua":72.0,"KLDatMua":81600.0,"KLTB1LenhMua":1133.33,"SoLenhDatBan":57.0,"KLDatBan":117100.0,"KLTB1LenhBan":2054.0,"ChenhLechKL":"-35,500","ThayDoi":"0.02(0.69 %)"},{"Date":"01\/11\/2024","GiaDieuChinh":2.91,"GiaDongCua":2.91,"KhoiLuongKhopLenh":48800.0,"GiaTriKhopLenh":137000000.0,"KLThoaThuan":0.0,"GtThoaThuan":0.0,"GiaMoCua":2.98,"GiaCaoNhat":2.98,"GiaThapNhat":2.79,"SoLenhMua":85.0,"KLDatMua":103900.0,"KLTB1LenhMua":1222.35,"SoLenhDatBan":55.0,"KLDatBan":170700.0,"KLTB1LenhBan":3104.0,"ChenhLechKL":"-66,800","ThayDoi":"-0.07(-2.35 %)"},{"Date":"31\/10\/2024","GiaDieuChinh":2.98,"GiaDongCua":2.98,"KhoiLuongKhopLenh":37600.0,"GiaTriKhopLenh":108000000.0,"KLThoaThuan":0.0,"GtThoaThuan":0.0,"GiaMoCua":2.89,"GiaCaoNhat":2.98,"GiaThapNhat":2.88,"SoLenhMua":63.0,"KLDatMua":84800.0,"KLTB1LenhMua":1346.03,"SoLenhDatBan":48.0,"KLDatBan":140100.0,"KLTB1LenhBan":2919.0,"ChenhLechKL":"-55,300","ThayDoi":"0.09(3.11 %)"},{"Date":"08\/10\/2024","GiaDieuChinh":null,"GiaDongCua":null,"KhoiLuongKhopLenh":null,"GiaTriKhopLenh":null,"KLThoaThuan":null,"GtThoaThuan":null,"GiaMoCua":null,"GiaCaoNhat":null,"GiaThapNhat":null,"SoLenhMua":89.0,"KLDatMua":137900.0,"KLTB1LenhMua":1549.44,"SoLenhDatBan":60.0,"KLDatBan":122000.0,"KLTB1LenhBan":2033.0,"ChenhLechKL":"15,900","ThayDoi":null}]