[{"Date":"15\/01\/2024","GiaDieuChinh":10.0,"GiaDongCua":10.0,"KhoiLuongKhopLenh":160900,"GiaTriKhopLenh":1627000000,"KLThoaThuan":0,"GtThoaThuan":0,"GiaMoCua":10.1,"GiaCaoNhat":10.3,"GiaThapNhat":10.0,"SoLenhMua":null,"KLDatMua":null,"KLTB1LenhMua":null,"SoLenhDatBan":null,"KLDatBan":null,"KLTB1LenhBan":null,"ChenhLechKL":null,"ThayDoi":"-0.1(-0.99 %)"},{"Date":"12\/01\/2024","GiaDieuChinh":10.1,"GiaDongCua":10.1,"KhoiLuongKhopLenh":393000,"GiaTriKhopLenh":4012000000,"KLThoaThuan":0,"GtThoaThuan":0,"GiaMoCua":10.3,"GiaCaoNhat":10.35,"GiaThapNhat":10.1,"SoLenhMua":null,"KLDatMua":null,"KLTB1LenhMua":null,"SoLenhDatBan":null,"KLDatBan":null,"KLTB1LenhBan":null,"ChenhLechKL":null,"ThayDoi":"-0.2(-1.94 %)"},{"Date":"02\/01\/2024","GiaDieuChinh":10.25,"GiaDongCua":10.25,"KhoiLuongKhopLenh":167700,"GiaTriKhopLenh":1722000000,"KLThoaThuan":0,"GtThoaThuan":0,"GiaMoCua":10.4,"GiaCaoNhat":10.5,"GiaThapNhat":10.2,"SoLenhMua":220.0,"KLDatMua":324100.0,"KLTB1LenhMua":1473.18,"SoLenhDatBan":226.0,"KLDatBan":732500.0,"KLTB1LenhBan":3241.0,"ChenhLechKL":"-408,400","ThayDoi":"0(0.00 %)"},{"Date":"11\/01\/2024","GiaDieuChinh":10.3,"GiaDongCua":10.3,"KhoiLuongKhopLenh":285000,"GiaTriKhopLenh":2951000000,"KLThoaThuan":0,"GtThoaThuan":0,"GiaMoCua":10.5,"GiaCaoNhat":10.5,"GiaThapNhat":10.25,"SoLenhMua":null,"KLDatMua":null,"KLTB1LenhMua":null,"SoLenhDatBan":null,"KLDatBan":null,"KLTB1LenhBan":null,"ChenhLechKL":null,"ThayDoi":"-0.1(-0.96 %)"},{"Date":"09\/01\/2024","GiaDieuChinh":10.4,"GiaDongCua":10.4,"KhoiLuongKhopLenh":420700,"GiaTriKhopLenh":4425000000,"KLThoaThuan":0,"GtThoaThuan":0,"GiaMoCua":10.55,"GiaCaoNhat":10.7,"GiaThapNhat":10.35,"SoLenhMua":494.0,"KLDatMua":756800.0,"KLTB1LenhMua":1531.98,"SoLenhDatBan":286.0,"KLDatBan":941600.0,"KLTB1LenhBan":3292.0,"ChenhLechKL":"-184,800","ThayDoi":"-0.2(-1.89 %)"},{"Date":"10\/01\/2024","GiaDieuChinh":10.4,"GiaDongCua":10.4,"KhoiLuongKhopLenh":316500,"GiaTriKhopLenh":3301000000,"KLThoaThuan":0,"GtThoaThuan":0,"GiaMoCua":10.6,"GiaCaoNhat":10.6,"GiaThapNhat":10.35,"SoLenhMua":0.0,"KLDatMua":0.0,"KLTB1LenhMua":0.0,"SoLenhDatBan":0.0,"KLDatBan":0.0,"KLTB1LenhBan":0.0,"ChenhLechKL":"0","ThayDoi":"0(0.00 %)"},{"Date":"04\/01\/2024","GiaDieuChinh":10.45,"GiaDongCua":10.45,"KhoiLuongKhopLenh":472100,"GiaTriKhopLenh":5060000000,"KLThoaThuan":0,"GtThoaThuan":0,"GiaMoCua":10.7,"GiaCaoNhat":10.9,"GiaThapNhat":10.45,"SoLenhMua":352.0,"KLDatMua":844500.0,"KLTB1LenhMua":2399.15,"SoLenhDatBan":487.0,"KLDatBan":1233300.0,"KLTB1LenhBan":2532.0,"ChenhLechKL":"-388,800","ThayDoi":"-0.25(-2.34 %)"},{"Date":"05\/01\/2024","GiaDieuChinh":10.6,"GiaDongCua":10.6,"KhoiLuongKhopLenh":467500,"GiaTriKhopLenh":4930000000,"KLThoaThuan":0,"GtThoaThuan":0,"GiaMoCua":10.45,"GiaCaoNhat":10.7,"GiaThapNhat":10.45,"SoLenhMua":452.0,"KLDatMua":1511500.0,"KLTB1LenhMua":3344.03,"SoLenhDatBan":348.0,"KLDatBan":887500.0,"KLTB1LenhBan":2550.0,"ChenhLechKL":"624,000","ThayDoi":"0.15(1.44 %)"},{"Date":"08\/01\/2024","GiaDieuChinh":10.6,"GiaDongCua":10.6,"KhoiLuongKhopLenh":535900,"GiaTriKhopLenh":5707000000,"KLThoaThuan":0,"GtThoaThuan":0,"GiaMoCua":10.65,"GiaCaoNhat":10.75,"GiaThapNhat":10.5,"SoLenhMua":398.0,"KLDatMua":976800.0,"KLTB1LenhMua":2454.27,"SoLenhDatBan":378.0,"KLDatBan":939500.0,"KLTB1LenhBan":2485.0,"ChenhLechKL":"37,300","ThayDoi":"0(0.00 %)"},{"Date":"03\/01\/2024","GiaDieuChinh":10.7,"GiaDongCua":10.7,"KhoiLuongKhopLenh":838600,"GiaTriKhopLenh":8900000000,"KLThoaThuan":0,"GtThoaThuan":0,"GiaMoCua":10.3,"GiaCaoNhat":10.8,"GiaThapNhat":10.25,"SoLenhMua":488.0,"KLDatMua":1440800.0,"KLTB1LenhMua":2952.46,"SoLenhDatBan":632.0,"KLDatBan":1642600.0,"KLTB1LenhBan":2599.0,"ChenhLechKL":"-201,800","ThayDoi":"0.45(4.39 %)"}]